Workbook

Sheet Data_Input
A1: DATA INPUT - historical financials. Fixed row keys in column A; one column per year. A Python extractor should write ONLY this tab. (You may hide this tab.)
A3: key | B3: label | C3: FY2021 | D3: FY2022 | E3: FY2023 | F3: FY2024 | G3: FY2025
A4: -- income_statement --
A5: revenue | B5: Revenue | C5: 365.817 | D5: 394.328 | E5: 383.285 | F5: 391.035 | G5: 416.161
A6: cogs | B6: Cogs | C6: 212.981 | D6: 223.546 | E6: 214.137 | F6: 210.352 | G6: 220.96
A7: salaries_and_benefits | B7: Salaries And Benefits | C7: 16.2796 | D7: 20.5739 | E7: 23.6322 | F7: 25.1224 | G7: 28.047
A8: rent_and_overhead | B8: Rent And Overhead | C8: 16.3234 | D8: 19.6671 | E8: 19.6958 | F8: 20.8996 | G8: 22.406
A9: d_and_a | B9: D And A | C9: 11.284 | D9: 11.104 | E9: 11.519 | F9: 11.445 | G9: 11.698
A10: interest | B10: Interest | C10: 2.645 | D10: 2.931 | E10: 3.933 | F10: 3.7784 | G10: 3.5664
A11: taxes | B11: Taxes | C11: 14.527 | D11: 19.3 | E11: 16.741 | F11: 29.749 | G11: 20.719
A12: -- balance_sheet --
A13: cash | B13: Cash | C13: 190.516 | D13: 169.109 | E13: 162.099 | F13: 156.65 | G13: 132.42
A14: accounts_receivable | B14: Accounts Receivable | C14: 51.506 | D14: 60.932 | E14: 60.985 | F14: 66.243 | G14: 72.957
A15: inventory | B15: Inventory | C15: 6.58 | D15: 4.946 | E15: 6.331 | F15: 7.286 | G15: 5.718
A16: ppe | B16: Ppe | C16: 102.4 | D16: 117.768 | E16: 123.168 | F16: 134.801 | G16: 148.146
A17: accounts_payable | B17: Accounts Payable | C17: 151.39 | D17: 169.603 | E17: 166.507 | F17: 188.971 | G17: 173.131
A18: debt | B18: Debt | C18: 136.522 | D18: 132.48 | E18: 123.93 | F18: 119.059 | G18: 112.377
A19: equity_capital | B19: Equity Capital | C19: 57.528 | D19: 53.74 | E19: 62.36 | F19: 76.104 | G19: 87.997
A20: retained_earnings | B20: Retained Earnings | C20: 5.562 | D20: -3.068 | E20: -0.214 | F20: -19.154 | G20: -14.264
A21: -- schedules --
A22: capex | B22: Capex | C22: 11.085 | D22: 10.708 | E22: 10.959 | F22: 9.447 | G22: 12.715
A23: debt_issuance | B23: Debt Issuance | C23: 12.665 | D23: -0.123 | E23: -9.901 | F23: -5.998 | G23: -8.483
A24: equity_issued | B24: Equity Issued | C24: -84.866 | D24: -89.402 | E24: -77.55 | F24: -94.949 | G24: -90.711
A25: -- opening_balances --
A26: ppe_opening_first | B26: Ppe Opening First | C26: 102.599
A27: debt_opening_first | B27: Debt Opening First | C27: 123.857
A28: nol_opening | B28: Nol Opening | C28: 0

Sheet Financial Model & DCF
A1: Apple Inc. (NASDAQ: AAPL) | D1: Historical Results | I1: Forecast Period
D2: 2021 | E2: 2022 | F2: 2023 | G2: 2024 | H2: 2025 | I2: 2026 | J2: 2027 | K2: 2028 | L2: 2029 | M2: 2030 | N2: 2031 | O2: 2032 | P2: 2033 | Q2: 2034 | R2: 2035
A3: Balance Sheet Check | D3: =IF(ABS(D60)<0.005,"OK","ERROR") -> OK | E3: =IF(ABS(E60)<0.005,"OK","ERROR") -> OK | F3: =IF(ABS(F60)<0.005,"OK","ERROR") -> OK | G3: =IF(ABS(G60)<0.005,"OK","ERROR") -> OK | H3: =IF(ABS(H60)<0.005,"OK","ERROR") -> OK | I3: =IF(ABS(I60)<0.005,"OK","ERROR") -> OK | J3: =IF(ABS(J60)<0.005,"OK","ERROR") -> OK | K3: =IF(ABS(K60)<0.005,"OK","ERROR") -> OK | ... R3: =IF(ABS(R60)<0.005,"OK","ERROR") -> OK
A4: All figures in USD billions unless noted | per-share values in USD | E4: Scenario: Prices 17-Jul-2026 (live quote). rf 4.55% = US 10Y as-of 17-Jul-2026 (was 4.30% - refreshed); terminal g = rf per Damodaran convention. AUDITED CONVENTIONS: per-share = equity / TODAY'S diluted count; capital returns modeled as equity outflows (count constant - no double count); treasury line includes ST+LT investments (in the equity bridge; their income excluded from FCF). DAMODARAN 10-YR: growth 6%->4.3%, opex fade CAVEAT: history trends UP (8.9%->12.1% FY21-25) - services-mix reversal is a named catalyst, treat as bull-leaning. S2C 3.5 with capex floor check. WACC 9.2%->8.6%, terminal g=rf 4.3%, exit 18x. Returns $105B/yr. Consensus $324. Forecast D&A anchored to FY2025 dollar level (~US$11.7B, 7.9% of the post-treasury-reclass 'PP&E & other' base), growing with the capex roll. Perennial NWC cash release reflects Apple's structural negative working capital (payables + deferred services > receivables + inventory); magnitude rides the broad folded payables line - directional, not precise. COGS%% derived from a SEGMENT-MIX build, not pinned: Services mix +~70bps/yr at a ~35pt gross-margin gap adds ~+25bps blended GM/yr, net of DRAM/NAND supercycle drag in FY26-27. GM path: 46.9 -> 46.7 (dip) -> 48.4 by FY2035 - direction-consistent with the 5-yr mix-driven expansion, dip named (memory costs).
A5: Assumptions | E5: Corporate actions: No dilutive actions found - searched 2026-07-17; buyback program modeled as capital returns (negative equity_issued), not count reduction. NEWS SCAN 2026-07-17 (FMP stock-news): DOJ antitrust EARLY SETTLEMENT talks (2024 suit) - de-risks App Store/Services tail; Apple v. OpenAI trade-secrets suit filed ~10-Jul (400+ ex-employees cited) - litigation overlay, no near-term P&L; ~$851B cumulative directed to buybacks (supports capital-return modeling); market narrative rewarding Apple's low-capex 'AI minimalist' stance amid AI-capex doubts - consistent with this deck's capex path.
A7: Key Assumptions
A8: Revenue Growth (% Change) | E8: =E26/D26-1 -> 0.077937876 | F8: =F26/E26-1 -> -0.028004605 | G8: =G26/F26-1 -> 0.020219941 | H8: =H26/G26-1 -> 0.064255118 | I8: 0.06 | J8: 0.058 | K8: 0.055 | L8: 0.052 | M8: 0.05 | N8: 0.048 | O8: 0.047 | P8: 0.045 | Q8: 0.044 | R8: 0.043
A9: Cost of Goods Sold (% of Revenue) | D9: =D27/D26 -> 0.5822064 | E9: =E27/E26 -> 0.56690369 | F9: =F27/F26 -> 0.5586887 | G9: =G27/G26 -> 0.5379365 | H9: =H27/H26 -> 0.53094836 | I9: 0.533 | J9: 0.5335 | K9: 0.531 | L9: 0.5285 | M9: 0.526 | N9: 0.524 | O9: 0.522 | P9: 0.52 | Q9: 0.518 | R9: 0.516
A10: Research & Development (% of Revenue) | D10: =D30/D26 -> 0.044502032 | E10: =E30/E26 -> 0.052174586 | F10: =F30/F26 -> 0.061656992 | G10: =G30/G26 -> 0.064245911 | H10: =H30/H26 -> 0.06739459 | I10: 0.0656 | J10: 0.0656 | K10: 0.065 | L10: 0.065 | M10: 0.0645 | N10: 0.0645 | O10: 0.064 | P10: 0.064 | Q10: 0.0634 | R10: 0.0634
A11: Selling, General & Administrative (USD billions) | D11: =D31 -> 16.3234 | E11: =E31 -> 19.6671 | F11: =F31 -> 19.6958 | G11: =G31 -> 20.8996 | H11: =H31 -> 22.406 | I11: 23.12 | J11: 24.46 | K11: 25.58 | L11: 26.91 | M11: 28.01 | N11: 29.35 | O11: 30.49 | P11: 31.87 | Q11: 32.97 | R11: 34.39
A12: Depreciation & Amortization (% of PP&E) | D12: =D32/D96 -> 0.10998158 | E12: =E32/E96 -> 0.1084375 | F12: =F32/F96 -> 0.11292694 | G12: =G32/G96 -> 0.11282087 | H12: =H32/H96 -> 0.11763168 | I12: 0.079 | J12: 0.079 | K12: 0.079 | L12: 0.079 | M12: 0.079 | N12: 0.079 | O12: 0.079 | P12: 0.079 | Q12: 0.079 | R12: 0.079
A13: Interest (% of Debt) | D13: =D33/AVERAGE(D102,D104) -> 0.020316539 | E13: =E33/AVERAGE(E102,E104) -> 0.021478743 | F13: =F33/AVERAGE(F102,F104) -> 0.029920463 | G13: =G33/AVERAGE(G102,G104) -> 0.03059458 | H13: =H33/AVERAGE(H102,H104) -> 0.030676467 | I13: 0.03 | J13: 0.03 | K13: 0.03 | L13: 0.03 | M13: 0.03 | N13: 0.03 | O13: 0.03 | P13: 0.03 | Q13: 0.03 | R13: 0.03
A14: Tax Rate (% of Earnings Before Tax) | D14: =IF(D35=0,0,D37/D35) -> 0.13665525 | E14: =IF(E35=0,0,E37/E35) -> 0.1656567 | F14: =IF(F35=0,0,F37/F35) -> 0.15168346 | G14: =IF(G35=0,0,G37/G35) -> 0.24907567 | H14: =IF(H35=0,0,H37/H35) -> 0.16001254 | I14: 0.17 | J14: 0.17 | K14: 0.17 | L14: 0.17 | M14: 0.17 | N14: 0.17 | O14: 0.17 | P14: 0.17 | Q14: 0.17 | R14: 0.17
A15: Accounts Receivable (Days) | D15: =D45/D26*D21 -> 51.390969 | E15: =E45/E26*E21 -> 56.400205 | F15: =F45/F26*F21 -> 58.075649 | G15: =G45/G26*G21 -> 61.83256 | H15: =H45/H26*H21 -> 63.987988 | I15: 58 | J15: 58 | K15: 58 | L15: 58 | M15: 58 | N15: 58 | O15: 58 | P15: 58 | Q15: 58 | R15: 58
A16: Inventory (Days) | D16: =D46/D27*D21 -> 11.276593 | E16: =E46/E27*E21 -> 8.0756981 | F16: =F46/F27*F21 -> 10.791292 | G16: =G46/G27*G21 -> 12.642571 | H16: =H46/H27*H21 -> 9.4454652 | I16: 10 | J16: 10 | K16: 10 | L16: 10 | M16: 10 | N16: 10 | O16: 10 | P16: 10 | Q16: 10 | R16: 10
A17: Accounts Payable (Days) | D17: =D51/D27*D21 -> 259.44732 | E17: =E51/E27*E21 -> 276.9233 | F17: =F51/F27*F21 -> 283.81389 | G17: =G51/G27*G21 -> 327.89997 | H17: =H51/H27*H21 -> 285.9921 | I17: 287 | J17: 287 | K17: 287 | L17: 287 | M17: 287 | N17: 287 | O17: 287 | P17: 287 | Q17: 287 | R17: 287
A18: Capital Expenditures (USD billions) | D18: =D97 -> 11.085 | E18: =E97 -> 10.708 | F18: =F97 -> 10.959 | G18: =G97 -> 9.447 | H18: =H97 -> 12.715 | I18: 13 | J18: 13.5 | K18: 14 | L18: 14.5 | M18: 15 | N18: 15 | O18: 15 | P18: 15 | Q18: 15 | R18: 15
A19: Debt Issuance (Repayment) (USD billions) | D19: =D103 -> 12.665 | E19: =E103 -> -0.123 | F19: =F103 -> -9.901 | G19: =G103 -> -5.998 | H19: =H103 -> -8.483 | I19: 0 | J19: 0 | K19: 0 | L19: 0 | M19: 0 | N19: 0 | O19: 0 | P19: 0 | Q19: 0 | R19: 0
A20: Equity Issued (Repaid) (USD billions) | D20: =D77 -> 0 | E20: =E77 -> -89.402 | F20: =F77 -> -77.55 | G20: =G77 -> -94.949 | H20: =H77 -> -90.711 | I20: -105 | J20: -105 | K20: -105 | L20: -105 | M20: -105 | N20: -105 | O20: -105 | P20: -105 | Q20: -105 | R20: -105
A21: Days in Period | D21: 365 | E21: 365 | F21: 365 | G21: 365 | H21: 365 | I21: 365 | J21: 365 | K21: 365 | L21: 365 | M21: 365 | N21: 365 | O21: 365 | P21: 365 | Q21: 365 | R21: 365
A24: Income Statement
A26: Revenue | D26: =Data_Input!C5 -> 365.817 | E26: =Data_Input!D5 -> 394.328 | F26: =Data_Input!E5 -> 383.285 | G26: =Data_Input!F5 -> 391.035 | H26: =Data_Input!G5 -> 416.161 | I26: =H26*(1+I8) -> 441.13066 | J26: =I26*(1+J8) -> 466.71624 | K26: =J26*(1+K8) -> 492.38563 | L26: =K26*(1+L8) -> 517.98968 | M26: =L26*(1+M8) -> 543.88917 | N26: =M26*(1+N8) -> 569.99585 | O26: =N26*(1+O8) -> 596.78565 | P26: =O26*(1+P8) -> 623.64101 | ... R26: =Q26*(1+R8) -> 679.0777
A27: Cost of Goods Sold (COGS) | D27: =Data_Input!C6 -> 212.981 | E27: =Data_Input!D6 -> 223.546 | F27: =Data_Input!E6 -> 214.137 | G27: =Data_Input!F6 -> 210.352 | H27: =Data_Input!G6 -> 220.96 | I27: =I26*I9 -> 235.12264 | J27: =J26*J9 -> 248.99311 | K27: =K26*K9 -> 261.45677 | L27: =L26*L9 -> 273.75755 | M27: =M26*M9 -> 286.0857 | N27: =N26*N9 -> 298.67782 | O27: =O26*O9 -> 311.52211 | P27: =P26*P9 -> 324.29332 | ... R27: =R26*R9 -> 350.4041
A28: Gross Profit | D28: =D26-D27 -> 152.836 | E28: =E26-E27 -> 170.782 | F28: =F26-F27 -> 169.148 | G28: =G26-G27 -> 180.683 | H28: =H26-H27 -> 195.201 | I28: =I26-I27 -> 206.00802 | J28: =J26-J27 -> 217.72313 | K28: =K26-K27 -> 230.92886 | ... R28: =R26-R27 -> 328.67361
A29: Expenses
A30: Research & Development | D30: =Data_Input!C7 -> 16.2796 | E30: =Data_Input!D7 -> 20.5739 | F30: =Data_Input!E7 -> 23.6322 | G30: =Data_Input!F7 -> 25.1224 | H30: =Data_Input!G7 -> 28.047 | I30: =I26*I10 -> 28.938171 | J30: =J26*J10 -> 30.616585 | K30: =K26*K10 -> 32.005066 | L30: =L26*L10 -> 33.669329 | M30: =M26*M10 -> 35.080851 | N30: =N26*N10 -> 36.764732 | O30: =O26*O10 -> 38.194282 | P30: =P26*P10 -> 39.913024 | ... R30: =R26*R10 -> 43.053526
A31: Selling, General & Administrative | D31: =Data_Input!C8 -> 16.3234 | E31: =Data_Input!D8 -> 19.6671 | F31: =Data_Input!E8 -> 19.6958 | G31: =Data_Input!F8 -> 20.8996 | H31: =Data_Input!G8 -> 22.406 | I31: =I11 -> 23.12 | J31: =J11 -> 24.46 | K31: =K11 -> 25.58 | L31: =L11 -> 26.91 | M31: =M11 -> 28.01 | N31: =N11 -> 29.35 | O31: =O11 -> 30.49 | P31: =P11 -> 31.87 | ... R31: =R11 -> 34.39
A32: Depreciation & Amortization | D32: =Data_Input!C9 -> 11.284 | E32: =Data_Input!D9 -> 11.104 | F32: =Data_Input!E9 -> 11.519 | G32: =Data_Input!F9 -> 11.445 | H32: =Data_Input!G9 -> 11.698 | I32: =I12*I96 -> 11.703534 | J32: =J12*J96 -> 11.805955 | K32: =K12*K96 -> 11.939784 | L32: =L12*L96 -> 12.102541 | M32: =M12*M96 -> 12.291941 | N32: =N12*N96 -> 12.505877 | O32: =O12*O96 -> 12.702913 | P32: =P12*P96 -> 12.884383 | ... R32: =R12*R96 -> 13.205447
A33: Interest | D33: =Data_Input!C10 -> 2.645 | E33: =Data_Input!D10 -> 2.931 | F33: =Data_Input!E10 -> 3.933 | G33: =Data_Input!F10 -> 3.7784 | H33: =Data_Input!G10 -> 3.5664 | I33: =I13*AVERAGE(I102,I104) -> 3.37131 | J33: =J13*AVERAGE(J102,J104) -> 3.37131 | K33: =K13*AVERAGE(K102,K104) -> 3.37131 | L33: =L13*AVERAGE(L102,L104) -> 3.37131 | M33: =M13*AVERAGE(M102,M104) -> 3.37131 | N33: =N13*AVERAGE(N102,N104) -> 3.37131 | O33: =O13*AVERAGE(O102,O104) -> 3.37131 | P33: =P13*AVERAGE(P102,P104) -> 3.37131 | ... R33: =R13*AVERAGE(R102,R104) -> 3.37131
A34: Total Expenses | D34: =SUM(D30:D33) -> 46.532 | E34: =SUM(E30:E33) -> 54.276 | F34: =SUM(F30:F33) -> 58.78 | G34: =SUM(G30:G33) -> 61.2454 | H34: =SUM(H30:H33) -> 65.7174 | I34: =SUM(I30:I33) -> 67.133015 | J34: =SUM(J30:J33) -> 70.25385 | K34: =SUM(K30:K33) -> 72.89616 | ... R34: =SUM(R30:R33) -> 94.020283
A35: Earnings Before Tax | D35: =D28-D34 -> 106.304 | E35: =E28-E34 -> 116.506 | F35: =F28-F34 -> 110.368 | G35: =G28-G34 -> 119.4376 | H35: =H28-H34 -> 129.4836 | I35: =I28-I34 -> 138.875 | J35: =J28-J34 -> 147.46928 | K35: =K28-K34 -> 158.0327 | ... R35: =R28-R34 -> 234.65333
A37: Taxes | D37: =Data_Input!C11 -> 14.527 | E37: =Data_Input!D11 -> 19.3 | F37: =Data_Input!E11 -> 16.741 | G37: =Data_Input!F11 -> 29.749 | H37: =Data_Input!G11 -> 20.719 | I37: =MAX(I35-I109,0)*I14 -> 23.60875 | J37: =MAX(J35-J109,0)*J14 -> 25.069777 | K37: =MAX(K35-K109,0)*K14 -> 26.865559 | L37: =MAX(L35-L109,0)*L14 -> 28.590422 | M37: =MAX(M35-M109,0)*M14 -> 30.438392 | N37: =MAX(N35-N109,0)*N14 -> 32.185438 | O37: =MAX(O35-O109,0)*O14 -> 34.085856 | P37: =MAX(P35-P109,0)*P14 -> 35.922524 | ... R37: =MAX(R35-R109,0)*R14 -> 39.891065
A38: Net Earnings | D38: =D35-D37 -> 91.777 | E38: =E35-E37 -> 97.206 | F38: =F35-F37 -> 93.627 | G38: =G35-G37 -> 89.6886 | H38: =H35-H37 -> 108.7646 | I38: =I35-I37 -> 115.26625 | J38: =J35-J37 -> 122.3995 | K38: =K35-K37 -> 131.16714 | ... R38: =R35-R37 -> 194.76226
A41: Balance Sheet
A43: Assets
A44: Cash | D44: =Data_Input!C13 -> 190.516 | E44: =Data_Input!D13 -> 169.109 | F44: =Data_Input!E13 -> 162.099 | G44: =Data_Input!F13 -> 156.65 | H44: =Data_Input!G13 -> 132.42 | I44: =I82 -> 155.27185 | J44: =J82 -> 177.43801 | K44: =K82 -> 206.92468 | L44: =L82 -> 244.38228 | M44: =M82 -> 290.52554 | N44: =N82 -> 345.57984 | O44: =O82 -> 410.19251 | P44: =P82 -> 483.88803 | ... R44: =R82 -> 661.12802
A45: Accounts Receivable | D45: =Data_Input!C14 -> 51.506 | E45: =Data_Input!D14 -> 60.932 | F45: =Data_Input!E14 -> 60.985 | G45: =Data_Input!F14 -> 66.243 | H45: =Data_Input!G14 -> 72.957 | I45: =I15/I21*I26 -> 70.097475 | J45: =J15/J21*J26 -> 74.163128 | K45: =K15/K21*K26 -> 78.2421 | L45: =L15/L21*L26 -> 82.31069 | M45: =M15/M21*M26 -> 86.426224 | N45: =N15/N21*N26 -> 90.574683 | O45: =O15/O21*O26 -> 94.831693 | P45: =P15/P21*P26 -> 99.099119 | ... R45: =R15/R21*R26 -> 107.90824
A46: Inventory | D46: =Data_Input!C15 -> 6.58 | E46: =Data_Input!D15 -> 4.946 | F46: =Data_Input!E15 -> 6.331 | G46: =Data_Input!F15 -> 7.286 | H46: =Data_Input!G15 -> 5.718 | I46: =I16/I21*I27 -> 6.4417162 | J46: =J16/J21*J27 -> 6.8217291 | K46: =K16/K21*K27 -> 7.1631992 | L46: =L16/L21*L27 -> 7.5002068 | M46: =M16/M21*M27 -> 7.8379645 | N46: =N16/N21*N27 -> 8.1829541 | O46: =O16/O21*O27 -> 8.5348524 | P46: =P16/P21*P27 -> 8.8847486 | ... R46: =R16/R21*R27 -> 9.6001122
A47: Property & Equipment | D47: =Data_Input!C16 -> 102.4 | E47: =Data_Input!D16 -> 117.768 | F47: =Data_Input!E16 -> 123.168 | G47: =Data_Input!F16 -> 134.801 | H47: =Data_Input!G16 -> 148.146 | I47: =I99 -> 149.44247 | J47: =J99 -> 151.13651 | K47: =K99 -> 153.19673 | L47: =L99 -> 155.59419 | M47: =M99 -> 158.30224 | N47: =N99 -> 160.79637 | O47: =O99 -> 163.09345 | P47: =P99 -> 165.20907 | ... R47: =R99 -> 168.95211
A48: Total Assets | D48: =SUM(D44:D47) -> 351.002 | E48: =SUM(E44:E47) -> 352.755 | F48: =SUM(F44:F47) -> 352.583 | G48: =SUM(G44:G47) -> 364.98 | H48: =SUM(H44:H47) -> 359.241 | I48: =SUM(I44:I47) -> 381.25351 | J48: =SUM(J44:J47) -> 409.55938 | K48: =SUM(K44:K47) -> 445.52671 | ... R48: =SUM(R44:R47) -> 947.58848
A50: Liabilities
A51: Accounts Payable | D51: =Data_Input!C17 -> 151.39 | E51: =Data_Input!D17 -> 169.603 | F51: =Data_Input!E17 -> 166.507 | G51: =Data_Input!F17 -> 188.971 | H51: =Data_Input!G17 -> 173.131 | I51: =I17/I21*I27 -> 184.87726 | J51: =J17/J21*J27 -> 195.78363 | K51: =K17/K21*K27 -> 205.58382 | L51: =L17/L21*L27 -> 215.25594 | M51: =M17/M21*M27 -> 224.94958 | N51: =N17/N21*N27 -> 234.85078 | O51: =O17/O21*O27 -> 244.95026 | P51: =P17/P21*P27 -> 254.99228 | ... R51: =R17/R21*R27 -> 275.52322
A52: Debt | D52: =Data_Input!C18 -> 136.522 | E52: =Data_Input!D18 -> 132.48 | F52: =Data_Input!E18 -> 123.93 | G52: =Data_Input!F18 -> 119.059 | H52: =Data_Input!G18 -> 112.377 | I52: =I104 -> 112.377 | J52: =J104 -> 112.377 | K52: =K104 -> 112.377 | L52: =L104 -> 112.377 | M52: =M104 -> 112.377 | N52: =N104 -> 112.377 | O52: =O104 -> 112.377 | P52: =P104 -> 112.377 | ... R52: =R104 -> 112.377
A53: Total Liabilities | D53: =D51+D52 -> 287.912 | E53: =E51+E52 -> 302.083 | F53: =F51+F52 -> 290.437 | G53: =G51+G52 -> 308.03 | H53: =H51+H52 -> 285.508 | I53: =I51+I52 -> 297.25426 | J53: =J51+J52 -> 308.16063 | K53: =K51+K52 -> 317.96082 | ... R53: =R51+R52 -> 387.90022
A54: Shareholder's Equity
A55: Equity Capital | D55: =Data_Input!C19 -> 57.528 | E55: =Data_Input!D19 -> 53.74 | F55: =Data_Input!E19 -> 62.36 | G55: =Data_Input!F19 -> 76.104 | H55: =Data_Input!G19 -> 87.997 | I55: =H55+I20 -> -17.003 | J55: =I55+J20 -> -122.003 | K55: =J55+K20 -> -227.003 | L55: =K55+L20 -> -332.003 | M55: =L55+M20 -> -437.003 | N55: =M55+N20 -> -542.003 | O55: =N55+O20 -> -647.003 | P55: =O55+P20 -> -752.003 | ... R55: =Q55+R20 -> -962.003
A56: Retained Earnings | D56: =Data_Input!C20 -> 5.562 | E56: =Data_Input!D20 -> -3.068 | F56: =Data_Input!E20 -> -0.214 | G56: =Data_Input!F20 -> -19.154 | H56: =Data_Input!G20 -> -14.264 | I56: =H56+I38 -> 101.00225 | J56: =I56+J38 -> 223.40175 | K56: =J56+K38 -> 354.56889 | L56: =K56+L38 -> 494.15743 | M56: =L56+M38 -> 642.7684 | N56: =M56+N38 -> 799.90906 | O56: =N56+O38 -> 966.32824 | P56: =O56+P38 -> 1141.7147 | ... R56: =Q56+R38 -> 1521.6913
A57: Shareholder's Equity | D57: =D55+D56 -> 63.09 | E57: =E55+E56 -> 50.672 | F57: =F55+F56 -> 62.146 | G57: =G55+G56 -> 56.95 | H57: =H55+H56 -> 73.733 | I57: =I55+I56 -> 83.999252 | J57: =J55+J56 -> 101.39875 | K57: =K55+K56 -> 127.56589 | ... R57: =R55+R56 -> 559.68826
A58: Total Liabilities & Shareholder's Equity | D58: =D53+D57 -> 351.002 | E58: =E53+E57 -> 352.755 | F58: =F53+F57 -> 352.583 | G58: =G53+G57 -> 364.98 | H58: =H53+H57 -> 359.241 | I58: =I53+I57 -> 381.25351 | J58: =J53+J57 -> 409.55938 | K58: =K53+K57 -> 445.52671 | ... R58: =R53+R57 -> 947.58848
A60: Check | D60: =D58-D48 -> 0 | E60: =E58-E48 -> 0 | F60: =F58-F48 -> 0 | G60: =G58-G48 -> 0 | H60: =H58-H48 -> 0 | I60: =I58-I48 -> 0 | J60: =J58-J48 -> 0 | K60: =K58-K48 -> 0 | ... R60: =R58-R48 -> 0
A63: Cash Flow Statement
A65: Operating Cash Flow
A66: Net Earnings | E66: =E38 -> 97.206 | F66: =F38 -> 93.627 | G66: =G38 -> 89.6886 | H66: =H38 -> 108.7646 | I66: =I38 -> 115.26625 | J66: =J38 -> 122.3995 | K66: =K38 -> 131.16714 | L66: =L38 -> 139.58853 | ... R66: =R38 -> 194.76226
A67: Plus: Depreciation & Amortization | E67: =E32 -> 11.104 | F67: =F32 -> 11.519 | G67: =G32 -> 11.445 | H67: =H32 -> 11.698 | I67: =I32 -> 11.703534 | J67: =J32 -> 11.805955 | K67: =K32 -> 11.939784 | L67: =L32 -> 12.102541 | ... R67: =R32 -> 13.205447
A68: Less: Changes in Working Capital | E68: =E93 -> -10.421 | F68: =F93 -> 4.534 | G68: =G93 -> -16.251 | H68: =H93 -> 20.986 | I68: =I93 -> -13.882064 | J68: =J93 -> -6.4607042 | K68: =K93 -> -5.3797486 | L68: =L93 -> -5.2665216 | ... R68: =R93 -> -5.5262988
A69: Cash from Operations | E69: =E66+E67-E68 -> 118.731 | F69: =F66+F67-F68 -> 100.612 | G69: =G66+G67-G68 -> 117.3846 | H69: =H66+H67-H68 -> 99.4766 | I69: =I66+I67-I68 -> 140.85185 | J69: =J66+J67-J68 -> 140.66616 | K69: =K66+K67-K68 -> 148.48667 | L69: =L66+L67-L68 -> 156.9576 | ... R69: =R66+R67-R68 -> 213.49401
A71: Investing Cash Flow
A72: Investments in Property & Equipment | E72: =E97 -> 10.708 | F72: =F97 -> 10.959 | G72: =G97 -> 9.447 | H72: =H97 -> 12.715 | I72: =I18 -> 13 | J72: =J18 -> 13.5 | K72: =K18 -> 14 | L72: =L18 -> 14.5 | M72: =M18 -> 15 | N72: =N18 -> 15 | O72: =O18 -> 15 | P72: =P18 -> 15 | ... R72: =R18 -> 15
A73: Cash from Investing | E73: =E72 -> 10.708 | F73: =F72 -> 10.959 | G73: =G72 -> 9.447 | H73: =H72 -> 12.715 | I73: =I72 -> 13 | J73: =J72 -> 13.5 | K73: =K72 -> 14 | L73: =L72 -> 14.5 | ... R73: =R72 -> 15
A75: Financing Cash Flow
A76: Issuance (repayment) of debt | E76: =E103 -> -0.123 | F76: =F103 -> -9.901 | G76: =G103 -> -5.998 | H76: =H103 -> -8.483 | I76: =I19 -> 0 | J76: =J19 -> 0 | K76: =K19 -> 0 | L76: =L19 -> 0 | M76: =M19 -> 0 | N76: =N19 -> 0 | O76: =O19 -> 0 | P76: =P19 -> 0 | ... R76: =R19 -> 0
A77: Issuance (repayment) of equity | E77: =Data_Input!D24 -> -89.402 | F77: =Data_Input!E24 -> -77.55 | G77: =Data_Input!F24 -> -94.949 | H77: =Data_Input!G24 -> -90.711 | I77: =I20 -> -105 | J77: =J20 -> -105 | K77: =K20 -> -105 | L77: =L20 -> -105 | M77: =M20 -> -105 | N77: =N20 -> -105 | O77: =O20 -> -105 | P77: =P20 -> -105 | ... R77: =R20 -> -105
A78: Cash from Financing | E78: =E76+E77 -> -89.525 | F78: =F76+F77 -> -87.451 | G78: =G76+G77 -> -100.947 | H78: =H76+H77 -> -99.194 | I78: =I76+I77 -> -105 | J78: =J76+J77 -> -105 | K78: =K76+K77 -> -105 | L78: =L76+L77 -> -105 | ... R78: =R76+R77 -> -105
A80: Net Increase (decrease) in Cash | E80: =E69-E73+E78 -> 18.498 | F80: =F69-F73+F78 -> 2.202 | G80: =G69-G73+G78 -> 6.9906 | H80: =H69-H73+H78 -> -12.4324 | I80: =I69-I73+I78 -> 22.851851 | J80: =J69-J73+J78 -> 22.166157 | K80: =K69-K73+K78 -> 29.486675 | L80: =L69-L73+L78 -> 37.457596 | ... R80: =R69-R73+R78 -> 93.494006
A81: Opening Cash Balance | E81: =D44 -> 190.516 | F81: =E44 -> 169.109 | G81: =F44 -> 162.099 | H81: =G44 -> 156.65 | I81: =H44 -> 132.42 | J81: =I44 -> 155.27185 | K81: =J44 -> 177.43801 | L81: =K44 -> 206.92468 | ... R81: =Q44 -> 567.63401
A82: Closing Cash Balance | E82: =E80+E81 -> 209.014 | F82: =F80+F81 -> 171.311 | G82: =G80+G81 -> 169.0896 | H82: =H80+H81 -> 144.2176 | I82: =I80+I81 -> 155.27185 | J82: =J80+J81 -> 177.43801 | K82: =K80+K81 -> 206.92468 | L82: =L80+L81 -> 244.38228 | ... R82: =R80+R81 -> 661.12802
A83: Historical CFS is PARTIAL: the 8-line schema omits dividends paid and securities flows, so computed historical cash movements do not reconcile to reported cash. Forecast years DO tie.
A86: Supporting Schedules
A88: Working Capital Schedule
A89: Accounts Receivable | D89: =D45 -> 51.506 | E89: =E45 -> 60.932 | F89: =F45 -> 60.985 | G89: =G45 -> 66.243 | H89: =H45 -> 72.957 | I89: =I45 -> 70.097475 | J89: =J45 -> 74.163128 | K89: =K45 -> 78.2421 | ... R89: =R45 -> 107.90824
A90: Inventory | D90: =D46 -> 6.58 | E90: =E46 -> 4.946 | F90: =F46 -> 6.331 | G90: =G46 -> 7.286 | H90: =H46 -> 5.718 | I90: =I46 -> 6.4417162 | J90: =J46 -> 6.8217291 | K90: =K46 -> 7.1631992 | ... R90: =R46 -> 9.6001122
A91: Accounts Payable | D91: =D51 -> 151.39 | E91: =E51 -> 169.603 | F91: =F51 -> 166.507 | G91: =G51 -> 188.971 | H91: =H51 -> 173.131 | I91: =I51 -> 184.87726 | J91: =J51 -> 195.78363 | K91: =K51 -> 205.58382 | ... R91: =R51 -> 275.52322
A92: Net Working Capital (NWC) | D92: =D89+D90-D91 -> -93.304 | E92: =E89+E90-E91 -> -103.725 | F92: =F89+F90-F91 -> -99.191 | G92: =G89+G90-G91 -> -115.442 | H92: =H89+H90-H91 -> -94.456 | I92: =I89+I90-I91 -> -108.33806 | J92: =J89+J90-J91 -> -114.79877 | K92: =K89+K90-K91 -> -120.17852 | ... R92: =R89+R90-R91 -> -158.01487
A93: Change in NWC | D93: =D92 -> -93.304 | E93: =E92-D92 -> -10.421 | F93: =F92-E92 -> 4.534 | G93: =G92-F92 -> -16.251 | H93: =H92-G92 -> 20.986 | I93: =I92-H92 -> -13.882064 | J93: =J92-I92 -> -6.4607042 | K93: =K92-J92 -> -5.3797486 | L93: =L92-K92 -> -5.2665216 | ... R93: =R92-Q92 -> -5.5262988
A95: Depreciation Schedule
A96: PPE Opening | D96: =Data_Input!C26 -> 102.599 | E96: =D99 -> 102.4 | F96: =E99 -> 102.004 | G96: =F99 -> 101.444 | H96: =G99 -> 99.446 | I96: =H47 -> 148.146 | J96: =I99 -> 149.44247 | K96: =J99 -> 151.13651 | L96: =K99 -> 153.19673 | M96: =L99 -> 155.59419 | N96: =M99 -> 158.30224 | O96: =N99 -> 160.79637 | P96: =O99 -> 163.09345 | Q96: =P99 -> 165.20907 | R96: =Q99 -> 167.15755
A97: Plus Capex | D97: =Data_Input!C22 -> 11.085 | E97: =Data_Input!D22 -> 10.708 | F97: =Data_Input!E22 -> 10.959 | G97: =Data_Input!F22 -> 9.447 | H97: =Data_Input!G22 -> 12.715 | I97: =I18 -> 13 | J97: =J18 -> 13.5 | K97: =K18 -> 14 | L97: =L18 -> 14.5 | M97: =M18 -> 15 | N97: =N18 -> 15 | O97: =O18 -> 15 | P97: =P18 -> 15 | ... R97: =R18 -> 15
A98: Less Depreciation | D98: =D32 -> 11.284 | E98: =E32 -> 11.104 | F98: =F32 -> 11.519 | G98: =G32 -> 11.445 | H98: =H32 -> 11.698 | I98: =I32 -> 11.703534 | J98: =J32 -> 11.805955 | K98: =K32 -> 11.939784 | ... R98: =R32 -> 13.205447
A99: PPE Closing | D99: =D96+D97-D98 -> 102.4 | E99: =E96+E97-E98 -> 102.004 | F99: =F96+F97-F98 -> 101.444 | G99: =G96+G97-G98 -> 99.446 | H99: =H96+H97-H98 -> 100.463 | I99: =I96+I97-I98 -> 149.44247 | J99: =J96+J97-J98 -> 151.13651 | K99: =K96+K97-K98 -> 153.19673 | ... R99: =R96+R97-R98 -> 168.95211
A101: Debt & Interest Schedule
A102: Debt Opening | D102: =Data_Input!C27 -> 123.857 | E102: =D104 -> 136.522 | F102: =E104 -> 136.399 | G102: =F104 -> 126.498 | H102: =G104 -> 120.5 | I102: =H52 -> 112.377 | J102: =I104 -> 112.377 | K102: =J104 -> 112.377 | L102: =K104 -> 112.377 | M102: =L104 -> 112.377 | N102: =M104 -> 112.377 | O102: =N104 -> 112.377 | P102: =O104 -> 112.377 | Q102: =P104 -> 112.377 | R102: =Q104 -> 112.377
A103: Issuance (repayment) | D103: =Data_Input!C23 -> 12.665 | E103: =Data_Input!D23 -> -0.123 | F103: =Data_Input!E23 -> -9.901 | G103: =Data_Input!F23 -> -5.998 | H103: =Data_Input!G23 -> -8.483 | I103: =I19 -> 0 | J103: =J19 -> 0 | K103: =K19 -> 0 | L103: =L19 -> 0 | M103: =M19 -> 0 | N103: =N19 -> 0 | O103: =O19 -> 0 | P103: =P19 -> 0 | ... R103: =R19 -> 0
A104: Debt Closing | D104: =D102+D103 -> 136.522 | E104: =E102+E103 -> 136.399 | F104: =F102+F103 -> 126.498 | G104: =G102+G103 -> 120.5 | H104: =H102+H103 -> 112.017 | I104: =I102+I103 -> 112.377 | J104: =J102+J103 -> 112.377 | K104: =K102+K103 -> 112.377 | ... R104: =R102+R103 -> 112.377
A105: Interest Expense | D105: =D33 -> 2.645 | E105: =E33 -> 2.931 | F105: =F33 -> 3.933 | G105: =G33 -> 3.7784 | H105: =H33 -> 3.5664 | I105: =I13*AVERAGE(I102,I104) -> 3.37131 | J105: =J13*AVERAGE(J102,J104) -> 3.37131 | K105: =K13*AVERAGE(K102,K104) -> 3.37131 | L105: =L13*AVERAGE(L102,L104) -> 3.37131 | M105: =M13*AVERAGE(M102,M104) -> 3.37131 | N105: =N13*AVERAGE(N102,N104) -> 3.37131 | O105: =O13*AVERAGE(O102,O104) -> 3.37131 | P105: =P13*AVERAGE(P102,P104) -> 3.37131 | ... R105: =R13*AVERAGE(R102,R104) -> 3.37131
A107: Tax Loss (NOL) Schedule
A108: NOL Opening | I108: =Data_Input!C28 -> 0 | J108: =I110 -> 0 | K108: =J110 -> 0 | L108: =K110 -> 0 | M108: =L110 -> 0 | N108: =M110 -> 0 | O108: =N110 -> 0 | P108: =O110 -> 0 | Q108: =P110 -> 0 | R108: =Q110 -> 0
A109: NOL Used | I109: =MIN(I108,MAX(I35,0)) -> 0 | J109: =MIN(J108,MAX(J35,0)) -> 0 | K109: =MIN(K108,MAX(K35,0)) -> 0 | L109: =MIN(L108,MAX(L35,0)) -> 0 | M109: =MIN(M108,MAX(M35,0)) -> 0 | N109: =MIN(N108,MAX(N35,0)) -> 0 | O109: =MIN(O108,MAX(O35,0)) -> 0 | P109: =MIN(P108,MAX(P35,0)) -> 0 | ... R109: =MIN(R108,MAX(R35,0)) -> 0
A110: NOL Closing | I110: =I108-I109 -> 0 | J110: =J108-J109 -> 0 | K110: =K108-K109 -> 0 | L110: =L108-L109 -> 0 | M110: =M108-M109 -> 0 | N110: =N108-N109 -> 0 | O110: =O108-O109 -> 0 | P110: =P108-P109 -> 0 | ... R110: =R108-R109 -> 0
A112: Revenue Build-Up Schedule
A113: No revenue build-up provided - revenue growth rates in Key Assumptions are direct inputs. For commodity/project companies, provide forecast.revenue_buildup so growth is derived.
A131: DCF Valuation
A133: Valuation Inputs
A134: Transaction Date | D134: 46219
A135: Current Share Price | D135: 333.74
A136: Shares Outstanding | D136: 14.688
A137: Market Capitalization | D137: =D135*D136 -> 4901.9731
A138: Perpetual Growth Rate | D138: 0.0432
A139: Exit EV/EBITDA Multiple | D139: 18
A140: Actual Market Cap (today) | D140: 4901.97
A141: Actual Shares Outstanding | D141: 14.688
...

Sheet Sensitivity
A1: Sensitivity & Scenarios - NASDAQ: AAPL
A3: All figures in USD billions | per-share values in USD
A5: Grid 1: Intrinsic Value per Share - WACC (rows) x Perpetual Growth (columns) - perpetuity TV only
B7: ='Financial Model & DCF'!$D$138+-0.005 -> 0.0382 | C7: ='Financial Model & DCF'!$D$138+-0.0025 -> 0.0407 | D7: ='Financial Model & DCF'!$D$138+0 -> 0.0432 | E7: ='Financial Model & DCF'!$D$138+0.0025 -> 0.0457 | F7: ='Financial Model & DCF'!$D$138+0.005 -> 0.0482
A8: ='Financial Model & DCF'!$R$149+-0.02 -> 0.0666 | B8: =(SUMPRODUCT('Financial Model & DCF'!$I$158:$R$158,(1+$A8)^-('Financial Model & DCF'!$I$148:$R$148))+'Financial Model & DCF'!$R$156*(1+B$7)/($A8-B$7)*(1+$A8)^-'Financial Model & DCF'!$R$148-('Financial Model & DCF'!$H$52-'Financial Model & DCF'!$H$44))/'Financial Model & DCF'!$D$136 -> 351.15398 | C8: =(SUMPRODUCT('Financial Model & DCF'!$I$158:$R$158,(1+$A8)^-('Financial Model & DCF'!$I$148:$R$148))+'Financial Model & DCF'!$R$156*(1+C$7)/($A8-C$7)*(1+$A8)^-'Financial Model & DCF'!$R$148-('Financial Model & DCF'!$H$52-'Financial Model & DCF'!$H$44))/'Financial Model & DCF'!$D$136 -> 378.61078 | D8: =(SUMPRODUCT('Financial Model & DCF'!$I$158:$R$158,(1+$A8)^-('Financial Model & DCF'!$I$148:$R$148))+'Financial Model & DCF'!$R$156*(1+D$7)/($A8-D$7)*(1+$A8)^-'Financial Model & DCF'!$R$148-('Financial Model & DCF'!$H$52-'Financial Model & DCF'!$H$44))/'Financial Model & DCF'!$D$136 -> 411.93442 | E8: =(SUMPRODUCT('Financial Model & DCF'!$I$158:$R$158,(1+$A8)^-('Financial Model & DCF'!$I$148:$R$148))+'Financial Model & DCF'!$R$156*(1+E$7)/($A8-E$7)*(1+$A8)^-'Financial Model & DCF'!$R$148-('Financial Model & DCF'!$H$52-'Financial Model & DCF'!$H$44))/'Financial Model & DCF'!$D$136 -> 453.23023 | F8: =(SUMPRODUCT('Financial Model & DCF'!$I$158:$R$158,(1+$A8)^-('Financial Model & DCF'!$I$148:$R$148))+'Financial Model & DCF'!$R$156*(1+F$7)/($A8-F$7)*(1+$A8)^-'Financial Model & DCF'!$R$148-('Financial Model & DCF'!$H$52-'Financial Model & DCF'!$H$44))/'Financial Model & DCF'!$D$136 -> 505.74771
A9: ='Financial Model & DCF'!$R$149+-0.01 -> 0.0766 | B9: =(SUMPRODUCT('Financial Model & DCF'!$I$158:$R$158,(1+$A9)^-('Financial Model & DCF'!$I$148:$R$148))+'Financial Model & DCF'!$R$156*(1+B$7)/($A9-B$7)*(1+$A9)^-'Financial Model & DCF'!$R$148-('Financial Model & DCF'!$H$52-'Financial Model & DCF'!$H$44))/'Financial Model & DCF'!$D$136 -> 258.89392 | C9: =(SUMPRODUCT('Financial Model & DCF'!$I$158:$R$158,(1+$A9)^-('Financial Model & DCF'!$I$148:$R$148))+'Financial Model & DCF'!$R$156*(1+C$7)/($A9-C$7)*(1+$A9)^-'Financial Model & DCF'!$R$148-('Financial Model & DCF'!$H$52-'Financial Model & DCF'!$H$44))/'Financial Model & DCF'!$D$136 -> 272.46519 | D9: =(SUMPRODUCT('Financial Model & DCF'!$I$158:$R$158,(1+$A9)^-('Financial Model & DCF'!$I$148:$R$148))+'Financial Model & DCF'!$R$156*(1+D$7)/($A9-D$7)*(1+$A9)^-'Financial Model & DCF'!$R$148-('Financial Model & DCF'!$H$52-'Financial Model & DCF'!$H$44))/'Financial Model & DCF'!$D$136 -> 288.06809 | E9: =(SUMPRODUCT('Financial Model & DCF'!$I$158:$R$158,(1+$A9)^-('Financial Model & DCF'!$I$148:$R$148))+'Financial Model & DCF'!$R$156*(1+E$7)/($A9-E$7)*(1+$A9)^-'Financial Model & DCF'!$R$148-('Financial Model & DCF'!$H$52-'Financial Model & DCF'!$H$44))/'Financial Model & DCF'!$D$136 -> 306.19573 | F9: =(SUMPRODUCT('Financial Model & DCF'!$I$158:$R$158,(1+$A9)^-('Financial Model & DCF'!$I$148:$R$148))+'Financial Model & DCF'!$R$156*(1+F$7)/($A9-F$7)*(1+$A9)^-'Financial Model & DCF'!$R$148-('Financial Model & DCF'!$H$52-'Financial Model & DCF'!$H$44))/'Financial Model & DCF'!$D$136 -> 327.51485
A10: ='Financial Model & DCF'!$R$149+0 -> 0.0866 | B10: =(SUMPRODUCT('Financial Model & DCF'!$I$158:$R$158,(1+$A10)^-('Financial Model & DCF'!$I$148:$R$148))+'Financial Model & DCF'!$R$156*(1+B$7)/($A10-B$7)*(1+$A10)^-'Financial Model & DCF'!$R$148-('Financial Model & DCF'!$H$52-'Financial Model & DCF'!$H$44))/'Financial Model & DCF'!$D$136 -> 204.81556 | C10: =(SUMPRODUCT('Financial Model & DCF'!$I$158:$R$158,(1+$A10)^-('Financial Model & DCF'!$I$148:$R$148))+'Financial Model & DCF'!$R$156*(1+C$7)/($A10-C$7)*(1+$A10)^-'Financial Model & DCF'!$R$148-('Financial Model & DCF'!$H$52-'Financial Model & DCF'!$H$44))/'Financial Model & DCF'!$D$136 -> 212.62237 | D10: =(SUMPRODUCT('Financial Model & DCF'!$I$158:$R$158,(1+$A10)^-('Financial Model & DCF'!$I$148:$R$148))+'Financial Model & DCF'!$R$156*(1+D$7)/($A10-D$7)*(1+$A10)^-'Financial Model & DCF'!$R$148-('Financial Model & DCF'!$H$52-'Financial Model & DCF'!$H$44))/'Financial Model & DCF'!$D$136 -> 221.32858 | E10: =(SUMPRODUCT('Financial Model & DCF'!$I$158:$R$158,(1+$A10)^-('Financial Model & DCF'!$I$148:$R$148))+'Financial Model & DCF'!$R$156*(1+E$7)/($A10-E$7)*(1+$A10)^-'Financial Model & DCF'!$R$148-('Financial Model & DCF'!$H$52-'Financial Model & DCF'!$H$44))/'Financial Model & DCF'!$D$136 -> 231.09912 | F10: =(SUMPRODUCT('Financial Model & DCF'!$I$158:$R$158,(1+$A10)^-('Financial Model & DCF'!$I$148:$R$148))+'Financial Model & DCF'!$R$156*(1+F$7)/($A10-F$7)*(1+$A10)^-'Financial Model & DCF'!$R$148-('Financial Model & DCF'!$H$52-'Financial Model & DCF'!$H$44))/'Financial Model & DCF'!$D$136 -> 242.14186
A11: ='Financial Model & DCF'!$R$149+0.01 -> 0.0966 | B11: =(SUMPRODUCT('Financial Model & DCF'!$I$158:$R$158,(1+$A11)^-('Financial Model & DCF'!$I$148:$R$148))+'Financial Model & DCF'!$R$156*(1+B$7)/($A11-B$7)*(1+$A11)^-'Financial Model & DCF'!$R$148-('Financial Model & DCF'!$H$52-'Financial Model & DCF'!$H$44))/'Financial Model & DCF'!$D$136 -> 169.30169 | C11: =(SUMPRODUCT('Financial Model & DCF'!$I$158:$R$158,(1+$A11)^-('Financial Model & DCF'!$I$148:$R$148))+'Financial Model & DCF'!$R$156*(1+C$7)/($A11-C$7)*(1+$A11)^-'Financial Model & DCF'!$R$148-('Financial Model & DCF'!$H$52-'Financial Model & DCF'!$H$44))/'Financial Model & DCF'!$D$136 -> 174.22995 | D11: =(SUMPRODUCT('Financial Model & DCF'!$I$158:$R$158,(1+$A11)^-('Financial Model & DCF'!$I$148:$R$148))+'Financial Model & DCF'!$R$156*(1+D$7)/($A11-D$7)*(1+$A11)^-'Financial Model & DCF'!$R$148-('Financial Model & DCF'!$H$52-'Financial Model & DCF'!$H$44))/'Financial Model & DCF'!$D$136 -> 179.61966 | E11: =(SUMPRODUCT('Financial Model & DCF'!$I$158:$R$158,(1+$A11)^-('Financial Model & DCF'!$I$148:$R$148))+'Financial Model & DCF'!$R$156*(1+E$7)/($A11-E$7)*(1+$A11)^-'Financial Model & DCF'!$R$148-('Financial Model & DCF'!$H$52-'Financial Model & DCF'!$H$44))/'Financial Model & DCF'!$D$136 -> 185.53881 | F11: =(SUMPRODUCT('Financial Model & DCF'!$I$158:$R$158,(1+$A11)^-('Financial Model & DCF'!$I$148:$R$148))+'Financial Model & DCF'!$R$156*(1+F$7)/($A11-F$7)*(1+$A11)^-'Financial Model & DCF'!$R$148-('Financial Model & DCF'!$H$52-'Financial Model & DCF'!$H$44))/'Financial Model & DCF'!$D$136 -> 192.06944
A12: ='Financial Model & DCF'!$R$149+0.02 -> 0.1066 | B12: =(SUMPRODUCT('Financial Model & DCF'!$I$158:$R$158,(1+$A12)^-('Financial Model & DCF'!$I$148:$R$148))+'Financial Model & DCF'!$R$156*(1+B$7)/($A12-B$7)*(1+$A12)^-'Financial Model & DCF'!$R$148-('Financial Model & DCF'!$H$52-'Financial Model & DCF'!$H$44))/'Financial Model & DCF'!$D$136 -> 144.20737 | C12: =(SUMPRODUCT('Financial Model & DCF'!$I$158:$R$158,(1+$A12)^-('Financial Model & DCF'!$I$148:$R$148))+'Financial Model & DCF'!$R$156*(1+C$7)/($A12-C$7)*(1+$A12)^-'Financial Model & DCF'!$R$148-('Financial Model & DCF'!$H$52-'Financial Model & DCF'!$H$44))/'Financial Model & DCF'!$D$136 -> 147.52066 | D12: =(SUMPRODUCT('Financial Model & DCF'!$I$158:$R$158,(1+$A12)^-('Financial Model & DCF'!$I$148:$R$148))+'Financial Model & DCF'!$R$156*(1+D$7)/($A12-D$7)*(1+$A12)^-'Financial Model & DCF'!$R$148-('Financial Model & DCF'!$H$52-'Financial Model & DCF'!$H$44))/'Financial Model & DCF'!$D$136 -> 151.09525 | E12: =(SUMPRODUCT('Financial Model & DCF'!$I$158:$R$158,(1+$A12)^-('Financial Model & DCF'!$I$148:$R$148))+'Financial Model & DCF'!$R$156*(1+E$7)/($A12-E$7)*(1+$A12)^-'Financial Model & DCF'!$R$148-('Financial Model & DCF'!$H$52-'Financial Model & DCF'!$H$44))/'Financial Model & DCF'!$D$136 -> 154.96333 | F12: =(SUMPRODUCT('Financial Model & DCF'!$I$158:$R$158,(1+$A12)^-('Financial Model & DCF'!$I$148:$R$148))+'Financial Model & DCF'!$R$156*(1+F$7)/($A12-F$7)*(1+$A12)^-'Financial Model & DCF'!$R$148-('Financial Model & DCF'!$H$52-'Financial Model & DCF'!$H$44))/'Financial Model & DCF'!$D$136 -> 159.16257
A15: Grid 2: Intrinsic Value per Share - WACC (rows) x Exit EV/EBITDA (columns) - exit-multiple TV only
B17: ='Financial Model & DCF'!$D$139+-1 -> 17 | C17: ='Financial Model & DCF'!$D$139+-0.5 -> 17.5 | D17: ='Financial Model & DCF'!$D$139+0 -> 18 | E17: ='Financial Model & DCF'!$D$139+0.5 -> 18.5 | F17: ='Financial Model & DCF'!$D$139+1 -> 19
A18: ='Financial Model & DCF'!$R$149+-0.02 -> 0.0666 | B18: =(SUMPRODUCT('Financial Model & DCF'!$I$158:$R$158,(1+$A18)^-('Financial Model & DCF'!$I$148:$R$148))+B$17*('Financial Model & DCF'!$R$151+'Financial Model & DCF'!$R$153)*(1+$A18)^-'Financial Model & DCF'!$R$148-('Financial Model & DCF'!$H$52-'Financial Model & DCF'!$H$44))/'Financial Model & DCF'!$D$136 -> 234.9771 | C18: =(SUMPRODUCT('Financial Model & DCF'!$I$158:$R$158,(1+$A18)^-('Financial Model & DCF'!$I$148:$R$148))+C$17*('Financial Model & DCF'!$R$151+'Financial Model & DCF'!$R$153)*(1+$A18)^-'Financial Model & DCF'!$R$148-('Financial Model & DCF'!$H$52-'Financial Model & DCF'!$H$44))/'Financial Model & DCF'!$D$136 -> 239.70362 | D18: =(SUMPRODUCT('Financial Model & DCF'!$I$158:$R$158,(1+$A18)^-('Financial Model & DCF'!$I$148:$R$148))+D$17*('Financial Model & DCF'!$R$151+'Financial Model & DCF'!$R$153)*(1+$A18)^-'Financial Model & DCF'!$R$148-('Financial Model & DCF'!$H$52-'Financial Model & DCF'!$H$44))/'Financial Model & DCF'!$D$136 -> 244.43013 | E18: =(SUMPRODUCT('Financial Model & DCF'!$I$158:$R$158,(1+$A18)^-('Financial Model & DCF'!$I$148:$R$148))+E$17*('Financial Model & DCF'!$R$151+'Financial Model & DCF'!$R$153)*(1+$A18)^-'Financial Model & DCF'!$R$148-('Financial Model & DCF'!$H$52-'Financial Model & DCF'!$H$44))/'Financial Model & DCF'!$D$136 -> 249.15665 | F18: =(SUMPRODUCT('Financial Model & DCF'!$I$158:$R$158,(1+$A18)^-('Financial Model & DCF'!$I$148:$R$148))+F$17*('Financial Model & DCF'!$R$151+'Financial Model & DCF'!$R$153)*(1+$A18)^-'Financial Model & DCF'!$R$148-('Financial Model & DCF'!$H$52-'Financial Model & DCF'!$H$44))/'Financial Model & DCF'!$D$136 -> 253.88317
A19: ='Financial Model & DCF'!$R$149+-0.01 -> 0.0766 | B19: =(SUMPRODUCT('Financial Model & DCF'!$I$158:$R$158,(1+$A19)^-('Financial Model & DCF'!$I$148:$R$148))+B$17*('Financial Model & DCF'!$R$151+'Financial Model & DCF'!$R$153)*(1+$A19)^-'Financial Model & DCF'!$R$148-('Financial Model & DCF'!$H$52-'Financial Model & DCF'!$H$44))/'Financial Model & DCF'!$D$136 -> 218.44572 | C19: =(SUMPRODUCT('Financial Model & DCF'!$I$158:$R$158,(1+$A19)^-('Financial Model & DCF'!$I$148:$R$148))+C$17*('Financial Model & DCF'!$R$151+'Financial Model & DCF'!$R$153)*(1+$A19)^-'Financial Model & DCF'!$R$148-('Financial Model & DCF'!$H$52-'Financial Model & DCF'!$H$44))/'Financial Model & DCF'!$D$136 -> 222.78349 | D19: =(SUMPRODUCT('Financial Model & DCF'!$I$158:$R$158,(1+$A19)^-('Financial Model & DCF'!$I$148:$R$148))+D$17*('Financial Model & DCF'!$R$151+'Financial Model & DCF'!$R$153)*(1+$A19)^-'Financial Model & DCF'!$R$148-('Financial Model & DCF'!$H$52-'Financial Model & DCF'!$H$44))/'Financial Model & DCF'!$D$136 -> 227.12126 | E19: =(SUMPRODUCT('Financial Model & DCF'!$I$158:$R$158,(1+$A19)^-('Financial Model & DCF'!$I$148:$R$148))+E$17*('Financial Model & DCF'!$R$151+'Financial Model & DCF'!$R$153)*(1+$A19)^-'Financial Model & DCF'!$R$148-('Financial Model & DCF'!$H$52-'Financial Model & DCF'!$H$44))/'Financial Model & DCF'!$D$136 -> 231.45903 | F19: =(SUMPRODUCT('Financial Model & DCF'!$I$158:$R$158,(1+$A19)^-('Financial Model & DCF'!$I$148:$R$148))+F$17*('Financial Model & DCF'!$R$151+'Financial Model & DCF'!$R$153)*(1+$A19)^-'Financial Model & DCF'!$R$148-('Financial Model & DCF'!$H$52-'Financial Model & DCF'!$H$44))/'Financial Model & DCF'!$D$136 -> 235.7968
A20: ='Financial Model & DCF'!$R$149+0 -> 0.0866 | B20: =(SUMPRODUCT('Financial Model & DCF'!$I$158:$R$158,(1+$A20)^-('Financial Model & DCF'!$I$148:$R$148))+B$17*('Financial Model & DCF'!$R$151+'Financial Model & DCF'!$R$153)*(1+$A20)^-'Financial Model & DCF'!$R$148-('Financial Model & DCF'!$H$52-'Financial Model & DCF'!$H$44))/'Financial Model & DCF'!$D$136 -> 203.32836 | C20: =(SUMPRODUCT('Financial Model & DCF'!$I$158:$R$158,(1+$A20)^-('Financial Model & DCF'!$I$148:$R$148))+C$17*('Financial Model & DCF'!$R$151+'Financial Model & DCF'!$R$153)*(1+$A20)^-'Financial Model & DCF'!$R$148-('Financial Model & DCF'!$H$52-'Financial Model & DCF'!$H$44))/'Financial Model & DCF'!$D$136 -> 207.31252 | D20: =(SUMPRODUCT('Financial Model & DCF'!$I$158:$R$158,(1+$A20)^-('Financial Model & DCF'!$I$148:$R$148))+D$17*('Financial Model & DCF'!$R$151+'Financial Model & DCF'!$R$153)*(1+$A20)^-'Financial Model & DCF'!$R$148-('Financial Model & DCF'!$H$52-'Financial Model & DCF'!$H$44))/'Financial Model & DCF'!$D$136 -> 211.29668 | E20: =(SUMPRODUCT('Financial Model & DCF'!$I$158:$R$158,(1+$A20)^-('Financial Model & DCF'!$I$148:$R$148))+E$17*('Financial Model & DCF'!$R$151+'Financial Model & DCF'!$R$153)*(1+$A20)^-'Financial Model & DCF'!$R$148-('Financial Model & DCF'!$H$52-'Financial Model & DCF'!$H$44))/'Financial Model & DCF'!$D$136 -> 215.28084 | F20: =(SUMPRODUCT('Financial Model & DCF'!$I$158:$R$158,(1+$A20)^-('Financial Model & DCF'!$I$148:$R$148))+F$17*('Financial Model & DCF'!$R$151+'Financial Model & DCF'!$R$153)*(1+$A20)^-'Financial Model & DCF'!$R$148-('Financial Model & DCF'!$H$52-'Financial Model & DCF'!$H$44))/'Financial Model & DCF'!$D$136 -> 219.26499
A21: ='Financial Model & DCF'!$R$149+0.01 -> 0.0966 | B21: =(SUMPRODUCT('Financial Model & DCF'!$I$158:$R$158,(1+$A21)^-('Financial Model & DCF'!$I$148:$R$148))+B$17*('Financial Model & DCF'!$R$151+'Financial Model & DCF'!$R$153)*(1+$A21)^-'Financial Model & DCF'!$R$148-('Financial Model & DCF'!$H$52-'Financial Model & DCF'!$H$44))/'Financial Model & DCF'!$D$136 -> 189.48991 | C21: =(SUMPRODUCT('Financial Model & DCF'!$I$158:$R$158,(1+$A21)^-('Financial Model & DCF'!$I$148:$R$148))+C$17*('Financial Model & DCF'!$R$151+'Financial Model & DCF'!$R$153)*(1+$A21)^-'Financial Model & DCF'!$R$148-('Financial Model & DCF'!$H$52-'Financial Model & DCF'!$H$44))/'Financial Model & DCF'!$D$136 -> 193.15213 | D21: =(SUMPRODUCT('Financial Model & DCF'!$I$158:$R$158,(1+$A21)^-('Financial Model & DCF'!$I$148:$R$148))+D$17*('Financial Model & DCF'!$R$151+'Financial Model & DCF'!$R$153)*(1+$A21)^-'Financial Model & DCF'!$R$148-('Financial Model & DCF'!$H$52-'Financial Model & DCF'!$H$44))/'Financial Model & DCF'!$D$136 -> 196.81435 | E21: =(SUMPRODUCT('Financial Model & DCF'!$I$158:$R$158,(1+$A21)^-('Financial Model & DCF'!$I$148:$R$148))+E$17*('Financial Model & DCF'!$R$151+'Financial Model & DCF'!$R$153)*(1+$A21)^-'Financial Model & DCF'!$R$148-('Financial Model & DCF'!$H$52-'Financial Model & DCF'!$H$44))/'Financial Model & DCF'!$D$136 -> 200.47658 | F21: =(SUMPRODUCT('Financial Model & DCF'!$I$158:$R$158,(1+$A21)^-('Financial Model & DCF'!$I$148:$R$148))+F$17*('Financial Model & DCF'!$R$151+'Financial Model & DCF'!$R$153)*(1+$A21)^-'Financial Model & DCF'!$R$148-('Financial Model & DCF'!$H$52-'Financial Model & DCF'!$H$44))/'Financial Model & DCF'!$D$136 -> 204.1388
A22: ='Financial Model & DCF'!$R$149+0.02 -> 0.1066 | B22: =(SUMPRODUCT('Financial Model & DCF'!$I$158:$R$158,(1+$A22)^-('Financial Model & DCF'!$I$148:$R$148))+B$17*('Financial Model & DCF'!$R$151+'Financial Model & DCF'!$R$153)*(1+$A22)^-'Financial Model & DCF'!$R$148-('Financial Model & DCF'!$H$52-'Financial Model & DCF'!$H$44))/'Financial Model & DCF'!$D$136 -> 176.80931 | C22: =(SUMPRODUCT('Financial Model & DCF'!$I$158:$R$158,(1+$A22)^-('Financial Model & DCF'!$I$148:$R$148))+C$17*('Financial Model & DCF'!$R$151+'Financial Model & DCF'!$R$153)*(1+$A22)^-'Financial Model & DCF'!$R$148-('Financial Model & DCF'!$H$52-'Financial Model & DCF'!$H$44))/'Financial Model & DCF'!$D$136 -> 180.17819 | D22: =(SUMPRODUCT('Financial Model & DCF'!$I$158:$R$158,(1+$A22)^-('Financial Model & DCF'!$I$148:$R$148))+D$17*('Financial Model & DCF'!$R$151+'Financial Model & DCF'!$R$153)*(1+$A22)^-'Financial Model & DCF'!$R$148-('Financial Model & DCF'!$H$52-'Financial Model & DCF'!$H$44))/'Financial Model & DCF'!$D$136 -> 183.54707 | E22: =(SUMPRODUCT('Financial Model & DCF'!$I$158:$R$158,(1+$A22)^-('Financial Model & DCF'!$I$148:$R$148))+E$17*('Financial Model & DCF'!$R$151+'Financial Model & DCF'!$R$153)*(1+$A22)^-'Financial Model & DCF'!$R$148-('Financial Model & DCF'!$H$52-'Financial Model & DCF'!$H$44))/'Financial Model & DCF'!$D$136 -> 186.91595 | F22: =(SUMPRODUCT('Financial Model & DCF'!$I$158:$R$158,(1+$A22)^-('Financial Model & DCF'!$I$148:$R$148))+F$17*('Financial Model & DCF'!$R$151+'Financial Model & DCF'!$R$153)*(1+$A22)^-'Financial Model & DCF'!$R$148-('Financial Model & DCF'!$H$52-'Financial Model & DCF'!$H$44))/'Financial Model & DCF'!$D$136 -> 190.28483
A25: Grid 3: Intrinsic Value per Share - WACC (rows) x FCF Deck Scale (columns) - stresses the revenue/margin deck
A26: Scales every forecast cash flow and the terminal value by the column factor - the growth deck is usually where the real risk lives, not the discount rate.
B28: 0.7 | C28: 0.85 | D28: 1 | E28: 1.15 | F28: 1.3
A29: ='Financial Model & DCF'!$R$149+-0.02 -> 0.0666 | B29: =(B$28*(SUMPRODUCT('Financial Model & DCF'!$I$158:$R$158,(1+$A29)^-('Financial Model & DCF'!$I$148:$R$148))+(('Financial Model & DCF'!$R$156*(1+'Financial Model & DCF'!$D$138)/($A29-'Financial Model & DCF'!$D$138)+'Financial Model & DCF'!$D$139*('Financial Model & DCF'!$R$151+'Financial Model & DCF'!$R$153))/2)*(1+$A29)^-'Financial Model & DCF'!$R$148)-('Financial Model & DCF'!$H$52-'Financial Model & DCF'!$H$44))/'Financial Model & DCF'!$D$136 -> 230.13697 | C29: =(C$28*(SUMPRODUCT('Financial Model & DCF'!$I$158:$R$158,(1+$A29)^-('Financial Model & DCF'!$I$148:$R$148))+(('Financial Model & DCF'!$R$156*(1+'Financial Model & DCF'!$D$138)/($A29-'Financial Model & DCF'!$D$138)+'Financial Model & DCF'!$D$139*('Financial Model & DCF'!$R$151+'Financial Model & DCF'!$R$153))/2)*(1+$A29)^-'Financial Model & DCF'!$R$148)-('Financial Model & DCF'!$H$52-'Financial Model & DCF'!$H$44))/'Financial Model & DCF'!$D$136 -> 279.15962 | D29: =(D$28*(SUMPRODUCT('Financial Model & DCF'!$I$158:$R$158,(1+$A29)^-('Financial Model & DCF'!$I$148:$R$148))+(('Financial Model & DCF'!$R$156*(1+'Financial Model & DCF'!$D$138)/($A29-'Financial Model & DCF'!$D$138)+'Financial Model & DCF'!$D$139*('Financial Model & DCF'!$R$151+'Financial Model & DCF'!$R$153))/2)*(1+$A29)^-'Financial Model & DCF'!$R$148)-('Financial Model & DCF'!$H$52-'Financial Model & DCF'!$H$44))/'Financial Model & DCF'!$D$136 -> 328.18228 | E29: =(E$28*(SUMPRODUCT('Financial Model & DCF'!$I$158:$R$158,(1+$A29)^-('Financial Model & DCF'!$I$148:$R$148))+(('Financial Model & DCF'!$R$156*(1+'Financial Model & DCF'!$D$138)/($A29-'Financial Model & DCF'!$D$138)+'Financial Model & DCF'!$D$139*('Financial Model & DCF'!$R$151+'Financial Model & DCF'!$R$153))/2)*(1+$A29)^-'Financial Model & DCF'!$R$148)-('Financial Model & DCF'!$H$52-'Financial Model & DCF'!$H$44))/'Financial Model & DCF'!$D$136 -> 377.20493 | F29: =(F$28*(SUMPRODUCT('Financial Model & DCF'!$I$158:$R$158,(1+$A29)^-('Financial Model & DCF'!$I$148:$R$148))+(('Financial Model & DCF'!$R$156*(1+'Financial Model & DCF'!$D$138)/($A29-'Financial Model & DCF'!$D$138)+'Financial Model & DCF'!$D$139*('Financial Model & DCF'!$R$151+'Financial Model & DCF'!$R$153))/2)*(1+$A29)^-'Financial Model & DCF'!$R$148)-('Financial Model & DCF'!$H$52-'Financial Model & DCF'!$H$44))/'Financial Model & DCF'!$D$136 -> 426.22759
A30: ='Financial Model & DCF'!$R$149+-0.01 -> 0.0766 | B30: =(B$28*(SUMPRODUCT('Financial Model & DCF'!$I$158:$R$158,(1+$A30)^-('Financial Model & DCF'!$I$148:$R$148))+(('Financial Model & DCF'!$R$156*(1+'Financial Model & DCF'!$D$138)/($A30-'Financial Model & DCF'!$D$138)+'Financial Model & DCF'!$D$139*('Financial Model & DCF'!$R$151+'Financial Model & DCF'!$R$153))/2)*(1+$A30)^-'Financial Model & DCF'!$R$148)-('Financial Model & DCF'!$H$52-'Financial Model & DCF'!$H$44))/'Financial Model & DCF'!$D$136 -> 180.72564 | C30: =(C$28*(SUMPRODUCT('Financial Model & DCF'!$I$158:$R$158,(1+$A30)^-('Financial Model & DCF'!$I$148:$R$148))+(('Financial Model & DCF'!$R$156*(1+'Financial Model & DCF'!$D$138)/($A30-'Financial Model & DCF'!$D$138)+'Financial Model & DCF'!$D$139*('Financial Model & DCF'!$R$151+'Financial Model & DCF'!$R$153))/2)*(1+$A30)^-'Financial Model & DCF'!$R$148)-('Financial Model & DCF'!$H$52-'Financial Model & DCF'!$H$44))/'Financial Model & DCF'!$D$136 -> 219.16016 | D30: =(D$28*(SUMPRODUCT('Financial Model & DCF'!$I$158:$R$158,(1+$A30)^-('Financial Model & DCF'!$I$148:$R$148))+(('Financial Model & DCF'!$R$156*(1+'Financial Model & DCF'!$D$138)/($A30-'Financial Model & DCF'!$D$138)+'Financial Model & DCF'!$D$139*('Financial Model & DCF'!$R$151+'Financial Model & DCF'!$R$153))/2)*(1+$A30)^-'Financial Model & DCF'!$R$148)-('Financial Model & DCF'!$H$52-'Financial Model & DCF'!$H$44))/'Financial Model & DCF'!$D$136 -> 257.59467 | E30: =(E$28*(SUMPRODUCT('Financial Model & DCF'!$I$158:$R$158,(1+$A30)^-('Financial Model & DCF'!$I$148:$R$148))+(('Financial Model & DCF'!$R$156*(1+'Financial Model & DCF'!$D$138)/($A30-'Financial Model & DCF'!$D$138)+'Financial Model & DCF'!$D$139*('Financial Model & DCF'!$R$151+'Financial Model & DCF'!$R$153))/2)*(1+$A30)^-'Financial Model & DCF'!$R$148)-('Financial Model & DCF'!$H$52-'Financial Model & DCF'!$H$44))/'Financial Model & DCF'!$D$136 -> 296.02918 | F30: =(F$28*(SUMPRODUCT('Financial Model & DCF'!$I$158:$R$158,(1+$A30)^-('Financial Model & DCF'!$I$148:$R$148))+(('Financial Model & DCF'!$R$156*(1+'Financial Model & DCF'!$D$138)/($A30-'Financial Model & DCF'!$D$138)+'Financial Model & DCF'!$D$139*('Financial Model & DCF'!$R$151+'Financial Model & DCF'!$R$153))/2)*(1+$A30)^-'Financial Model & DCF'!$R$148)-('Financial Model & DCF'!$H$52-'Financial Model & DCF'!$H$44))/'Financial Model & DCF'!$D$136 -> 334.4637
A31: ='Financial Model & DCF'!$R$149+0 -> 0.0866 | B31: =(B$28*(SUMPRODUCT('Financial Model & DCF'!$I$158:$R$158,(1+$A31)^-('Financial Model & DCF'!$I$148:$R$148))+(('Financial Model & DCF'!$R$156*(1+'Financial Model & DCF'!$D$138)/($A31-'Financial Model & DCF'!$D$138)+'Financial Model & DCF'!$D$139*('Financial Model & DCF'!$R$151+'Financial Model & DCF'!$R$153))/2)*(1+$A31)^-'Financial Model & DCF'!$R$148)-('Financial Model & DCF'!$H$52-'Financial Model & DCF'!$H$44))/'Financial Model & DCF'!$D$136 -> 151.82822 | C31: =(C$28*(SUMPRODUCT('Financial Model & DCF'!$I$158:$R$158,(1+$A31)^-('Financial Model & DCF'!$I$148:$R$148))+(('Financial Model & DCF'!$R$156*(1+'Financial Model & DCF'!$D$138)/($A31-'Financial Model & DCF'!$D$138)+'Financial Model & DCF'!$D$139*('Financial Model & DCF'!$R$151+'Financial Model & DCF'!$R$153))/2)*(1+$A31)^-'Financial Model & DCF'!$R$148)-('Financial Model & DCF'!$H$52-'Financial Model & DCF'!$H$44))/'Financial Model & DCF'!$D$136 -> 184.07042 | D31: =(D$28*(SUMPRODUCT('Financial Model & DCF'!$I$158:$R$158,(1+$A31)^-('Financial Model & DCF'!$I$148:$R$148))+(('Financial Model & DCF'!$R$156*(1+'Financial Model & DCF'!$D$138)/($A31-'Financial Model & DCF'!$D$138)+'Financial Model & DCF'!$D$139*('Financial Model & DCF'!$R$151+'Financial Model & DCF'!$R$153))/2)*(1+$A31)^-'Financial Model & DCF'!$R$148)-('Financial Model & DCF'!$H$52-'Financial Model & DCF'!$H$44))/'Financial Model & DCF'!$D$136 -> 216.31263 | E31: =(E$28*(SUMPRODUCT('Financial Model & DCF'!$I$158:$R$158,(1+$A31)^-('Financial Model & DCF'!$I$148:$R$148))+(('Financial Model & DCF'!$R$156*(1+'Financial Model & DCF'!$D$138)/($A31-'Financial Model & DCF'!$D$138)+'Financial Model & DCF'!$D$139*('Financial Model & DCF'!$R$151+'Financial Model & DCF'!$R$153))/2)*(1+$A31)^-'Financial Model & DCF'!$R$148)-('Financial Model & DCF'!$H$52-'Financial Model & DCF'!$H$44))/'Financial Model & DCF'!$D$136 -> 248.55484 | F31: =(F$28*(SUMPRODUCT('Financial Model & DCF'!$I$158:$R$158,(1+$A31)^-('Financial Model & DCF'!$I$148:$R$148))+(('Financial Model & DCF'!$R$156*(1+'Financial Model & DCF'!$D$138)/($A31-'Financial Model & DCF'!$D$138)+'Financial Model & DCF'!$D$139*('Financial Model & DCF'!$R$151+'Financial Model & DCF'!$R$153))/2)*(1+$A31)^-'Financial Model & DCF'!$R$148)-('Financial Model & DCF'!$H$52-'Financial Model & DCF'!$H$44))/'Financial Model & DCF'!$D$136 -> 280.79704
A32: ='Financial Model & DCF'!$R$149+0.01 -> 0.0966 | B32: =(B$28*(SUMPRODUCT('Financial Model & DCF'!$I$158:$R$158,(1+$A32)^-('Financial Model & DCF'!$I$148:$R$148))+(('Financial Model & DCF'!$R$156*(1+'Financial Model & DCF'!$D$138)/($A32-'Financial Model & DCF'!$D$138)+'Financial Model & DCF'!$D$139*('Financial Model & DCF'!$R$151+'Financial Model & DCF'!$R$153))/2)*(1+$A32)^-'Financial Model & DCF'!$R$148)-('Financial Model & DCF'!$H$52-'Financial Model & DCF'!$H$44))/'Financial Model & DCF'!$D$136 -> 132.16128 | C32: =(C$28*(SUMPRODUCT('Financial Model & DCF'!$I$158:$R$158,(1+$A32)^-('Financial Model & DCF'!$I$148:$R$148))+(('Financial Model & DCF'!$R$156*(1+'Financial Model & DCF'!$D$138)/($A32-'Financial Model & DCF'!$D$138)+'Financial Model & DCF'!$D$139*('Financial Model & DCF'!$R$151+'Financial Model & DCF'!$R$153))/2)*(1+$A32)^-'Financial Model & DCF'!$R$148)-('Financial Model & DCF'!$H$52-'Financial Model & DCF'!$H$44))/'Financial Model & DCF'!$D$136 -> 160.18914 | D32: =(D$28*(SUMPRODUCT('Financial Model & DCF'!$I$158:$R$158,(1+$A32)^-('Financial Model & DCF'!$I$148:$R$148))+(('Financial Model & DCF'!$R$156*(1+'Financial Model & DCF'!$D$138)/($A32-'Financial Model & DCF'!$D$138)+'Financial Model & DCF'!$D$139*('Financial Model & DCF'!$R$151+'Financial Model & DCF'!$R$153))/2)*(1+$A32)^-'Financial Model & DCF'!$R$148)-('Financial Model & DCF'!$H$52-'Financial Model & DCF'!$H$44))/'Financial Model & DCF'!$D$136 -> 188.21701 | E32: =(E$28*(SUMPRODUCT('Financial Model & DCF'!$I$158:$R$158,(1+$A32)^-('Financial Model & DCF'!$I$148:$R$148))+(('Financial Model & DCF'!$R$156*(1+'Financial Model & DCF'!$D$138)/($A32-'Financial Model & DCF'!$D$138)+'Financial Model & DCF'!$D$139*('Financial Model & DCF'!$R$151+'Financial Model & DCF'!$R$153))/2)*(1+$A32)^-'Financial Model & DCF'!$R$148)-('Financial Model & DCF'!$H$52-'Financial Model & DCF'!$H$44))/'Financial Model & DCF'!$D$136 -> 216.24487 | F32: =(F$28*(SUMPRODUCT('Financial Model & DCF'!$I$158:$R$158,(1+$A32)^-('Financial Model & DCF'!$I$148:$R$148))+(('Financial Model & DCF'!$R$156*(1+'Financial Model & DCF'!$D$138)/($A32-'Financial Model & DCF'!$D$138)+'Financial Model & DCF'!$D$139*('Financial Model & DCF'!$R$151+'Financial Model & DCF'!$R$153))/2)*(1+$A32)^-'Financial Model & DCF'!$R$148)-('Financial Model & DCF'!$H$52-'Financial Model & DCF'!$H$44))/'Financial Model & DCF'!$D$136 -> 244.27273
A33: ='Financial Model & DCF'!$R$149+0.02 -> 0.1066 | B33: =(B$28*(SUMPRODUCT('Financial Model & DCF'!$I$158:$R$158,(1+$A33)^-('Financial Model & DCF'!$I$148:$R$148))+(('Financial Model & DCF'!$R$156*(1+'Financial Model & DCF'!$D$138)/($A33-'Financial Model & DCF'!$D$138)+'Financial Model & DCF'!$D$139*('Financial Model & DCF'!$R$151+'Financial Model & DCF'!$R$153))/2)*(1+$A33)^-'Financial Model & DCF'!$R$148)-('Financial Model & DCF'!$H$52-'Financial Model & DCF'!$H$44))/'Financial Model & DCF'!$D$136 -> 117.53419 | C33: =(C$28*(SUMPRODUCT('Financial Model & DCF'!$I$158:$R$158,(1+$A33)^-('Financial Model & DCF'!$I$148:$R$148))+(('Financial Model & DCF'!$R$156*(1+'Financial Model & DCF'!$D$138)/($A33-'Financial Model & DCF'!$D$138)+'Financial Model & DCF'!$D$139*('Financial Model & DCF'!$R$151+'Financial Model & DCF'!$R$153))/2)*(1+$A33)^-'Financial Model & DCF'!$R$148)-('Financial Model & DCF'!$H$52-'Financial Model & DCF'!$H$44))/'Financial Model & DCF'!$D$136 -> 142.42768 | D33: =(D$28*(SUMPRODUCT('Financial Model & DCF'!$I$158:$R$158,(1+$A33)^-('Financial Model & DCF'!$I$148:$R$148))+(('Financial Model & DCF'!$R$156*(1+'Financial Model & DCF'!$D$138)/($A33-'Financial Model & DCF'!$D$138)+'Financial Model & DCF'!$D$139*('Financial Model & DCF'!$R$151+'Financial Model & DCF'!$R$153))/2)*(1+$A33)^-'Financial Model & DCF'!$R$148)-('Financial Model & DCF'!$H$52-'Financial Model & DCF'!$H$44))/'Financial Model & DCF'!$D$136 -> 167.32116 | E33: =(E$28*(SUMPRODUCT('Financial Model & DCF'!$I$158:$R$158,(1+$A33)^-('Financial Model & DCF'!$I$148:$R$148))+(('Financial Model & DCF'!$R$156*(1+'Financial Model & DCF'!$D$138)/($A33-'Financial Model & DCF'!$D$138)+'Financial Model & DCF'!$D$139*('Financial Model & DCF'!$R$151+'Financial Model & DCF'!$R$153))/2)*(1+$A33)^-'Financial Model & DCF'!$R$148)-('Financial Model & DCF'!$H$52-'Financial Model & DCF'!$H$44))/'Financial Model & DCF'!$D$136 -> 192.21465 | F33: =(F$28*(SUMPRODUCT('Financial Model & DCF'!$I$158:$R$158,(1+$A33)^-('Financial Model & DCF'!$I$148:$R$148))+(('Financial Model & DCF'!$R$156*(1+'Financial Model & DCF'!$D$138)/($A33-'Financial Model & DCF'!$D$138)+'Financial Model & DCF'!$D$139*('Financial Model & DCF'!$R$151+'Financial Model & DCF'!$R$153))/2)*(1+$A33)^-'Financial Model & DCF'!$R$148)-('Financial Model & DCF'!$H$52-'Financial Model & DCF'!$H$44))/'Financial Model & DCF'!$D$136 -> 217.10814
A35: Scenarios: Implied Value per Share - Bear / Base / Bull
A36: Bear = higher WACC, lower terminal growth; Bull = the reverse. Blue offsets are editable. Terminal value = average of perpetuity and exit-multiple, like the DCF.
B38: Today | C38: =YEAR('Financial Model & DCF'!I$145) -> 2026 | D38: =YEAR('Financial Model & DCF'!J$145) -> 2027 | E38: =YEAR('Financial Model & DCF'!K$145) -> 2028 | F38: =YEAR('Financial Model & DCF'!L$145) -> 2029 | G38: =YEAR('Financial Model & DCF'!M$145) -> 2030 | H38: =YEAR('Financial Model & DCF'!N$145) -> 2031 | I38: =YEAR('Financial Model & DCF'!O$145) -> 2032 | J38: =YEAR('Financial Model & DCF'!P$145) -> 2033 | ... L38: =YEAR('Financial Model & DCF'!R$145) -> 2035 | N38: WACC | O38: Growth | P38: Prob.
A39: Bear implied EV | B39: =SUMPRODUCT('Financial Model & DCF'!$I$158:$R$158,(1+$N39)^-('Financial Model & DCF'!$I$148:$R$148))+(('Financial Model & DCF'!$R$156*(1+$O39)/($N39-$O39)+'Financial Model & DCF'!$D$139*('Financial Model & DCF'!$R$151+'Financial Model & DCF'!$R$153))/2)*(1+$N39)^-'Financial Model & DCF'!$R$148 -> 2386.9856 | C39: =B39*(1+$N39)^'Financial Model & DCF'!I$147-'Financial Model & DCF'!I$158 -> 2409.3874 | D39: =C39*(1+$N39)^'Financial Model & DCF'!J$147-'Financial Model & DCF'!J$158 -> 2536.2638 | E39: =D39*(1+$N39)^'Financial Model & DCF'!K$147-'Financial Model & DCF'!K$158 -> 2669.3446 | F39: =E39*(1+$N39)^'Financial Model & DCF'!L$147-'Financial Model & DCF'!L$158 -> 2808.641 | G39: =F39*(1+$N39)^'Financial Model & DCF'!M$147-'Financial Model & DCF'!M$158 -> 2954.1007 | H39: =G39*(1+$N39)^'Financial Model & DCF'!N$147-'Financial Model & DCF'!N$158 -> 3106.1553 | I39: =H39*(1+$N39)^'Financial Model & DCF'!O$147-'Financial Model & DCF'!O$158 -> 3264.8606 | J39: =I39*(1+$N39)^'Financial Model & DCF'!P$147-'Financial Model & DCF'!P$158 -> 3431.401 | ... L39: =K39*(1+$N39)^'Financial Model & DCF'!R$147-'Financial Model & DCF'!R$158 -> 3788.7137 | N39: ='Financial Model & DCF'!$R$149+0.02 -> 0.1066 | O39: ='Financial Model & DCF'!$D$138+-0.005 -> 0.0382 | P39: 0.25
A40: Bear | B40: =(B39-('Financial Model & DCF'!$H$52-'Financial Model & DCF'!$H$44))/'Financial Model & DCF'!$D$136 -> 163.87722 | C40: =(C39-('Financial Model & DCF'!$H$52-'Financial Model & DCF'!$H$44))/'Financial Model & DCF'!$D$136 -> 165.4024 | D40: =(D39-('Financial Model & DCF'!$H$52-'Financial Model & DCF'!$H$44))/'Financial Model & DCF'!$D$136 -> 174.04049 | E40: =(E39-('Financial Model & DCF'!$H$52-'Financial Model & DCF'!$H$44))/'Financial Model & DCF'!$D$136 -> 183.10101 | F40: =(F39-('Financial Model & DCF'!$H$52-'Financial Model & DCF'!$H$44))/'Financial Model & DCF'!$D$136 -> 192.58469 | G40: =(G39-('Financial Model & DCF'!$H$52-'Financial Model & DCF'!$H$44))/'Financial Model & DCF'!$D$136 -> 202.48799 | H40: =(H39-('Financial Model & DCF'!$H$52-'Financial Model & DCF'!$H$44))/'Financial Model & DCF'!$D$136 -> 212.8403 | I40: =(I39-('Financial Model & DCF'!$H$52-'Financial Model & DCF'!$H$44))/'Financial Model & DCF'!$D$136 -> 223.6454 | ... L40: =(L39-('Financial Model & DCF'!$H$52-'Financial Model & DCF'!$H$44))/'Financial Model & DCF'!$D$136 -> 259.31078
A41: Base implied EV | B41: =SUMPRODUCT('Financial Model & DCF'!$I$158:$R$158,(1+$N41)^-('Financial Model & DCF'!$I$148:$R$148))+(('Financial Model & DCF'!$R$156*(1+$O41)/($N41-$O41)+'Financial Model & DCF'!$D$139*('Financial Model & DCF'!$R$151+'Financial Model & DCF'!$R$153))/2)*(1+$N41)^-'Financial Model & DCF'!$R$148 -> 3157.1569 | C41: =B41*(1+$N41)^'Financial Model & DCF'!I$147-'Financial Model & DCF'!I$158 -> 3183.5351 | D41: =C41*(1+$N41)^'Financial Model & DCF'!J$147-'Financial Model & DCF'!J$158 -> 3329.2649 | E41: =D41*(1+$N41)^'Financial Model & DCF'!K$147-'Financial Model & DCF'!K$158 -> 3480.2944 | F41: =E41*(1+$N41)^'Financial Model & DCF'!L$147-'Financial Model & DCF'!L$158 -> 3636.4321 | G41: =F41*(1+$N41)^'Financial Model & DCF'!M$147-'Financial Model & DCF'!M$158 -> 3797.4056 | H41: =G41*(1+$N41)^'Financial Model & DCF'!N$147-'Financial Model & DCF'!N$158 -> 3963.4085 | I41: =H41*(1+$N41)^'Financial Model & DCF'!O$147-'Financial Model & DCF'!O$158 -> 4134.2288 | J41: =I41*(1+$N41)^'Financial Model & DCF'!P$147-'Financial Model & DCF'!P$158 -> 4310.7593 | ... L41: =K41*(1+$N41)^'Financial Model & DCF'!R$147-'Financial Model & DCF'!R$158 -> 4680.2875 | N41: ='Financial Model & DCF'!$R$149 -> 0.0866 | O41: ='Financial Model & DCF'!$D$138 -> 0.0432 | P41: 0.5
A42: Base | B42: =(B41-('Financial Model & DCF'!$H$52-'Financial Model & DCF'!$H$44))/'Financial Model & DCF'!$D$136 -> 216.31263 | C42: =(C41-('Financial Model & DCF'!$H$52-'Financial Model & DCF'!$H$44))/'Financial Model & DCF'!$D$136 -> 218.10853 | D42: =(D41-('Financial Model & DCF'!$H$52-'Financial Model & DCF'!$H$44))/'Financial Model & DCF'!$D$136 -> 228.03022 | E42: =(E41-('Financial Model & DCF'!$H$52-'Financial Model & DCF'!$H$44))/'Financial Model & DCF'!$D$136 -> 238.31273 | F42: =(F41-('Financial Model & DCF'!$H$52-'Financial Model & DCF'!$H$44))/'Financial Model & DCF'!$D$136 -> 248.94302 | G42: =(G41-('Financial Model & DCF'!$H$52-'Financial Model & DCF'!$H$44))/'Financial Model & DCF'!$D$136 -> 259.90255 | H42: =(H41-('Financial Model & DCF'!$H$52-'Financial Model & DCF'!$H$44))/'Financial Model & DCF'!$D$136 -> 271.20448 | I42: =(I41-('Financial Model & DCF'!$H$52-'Financial Model & DCF'!$H$44))/'Financial Model & DCF'!$D$136 -> 282.83441 | ... L42: =(L41-('Financial Model & DCF'!$H$52-'Financial Model & DCF'!$H$44))/'Financial Model & DCF'!$D$136 -> 320.01161
A43: Bull implied EV | B43: =SUMPRODUCT('Financial Model & DCF'!$I$158:$R$158,(1+$N43)^-('Financial Model & DCF'!$I$148:$R$148))+(('Financial Model & DCF'!$R$156*(1+$O43)/($N43-$O43)+'Financial Model & DCF'!$D$139*('Financial Model & DCF'!$R$151+'Financial Model & DCF'!$R$153))/2)*(1+$N43)^-'Financial Model & DCF'!$R$148 -> 5489.2631 | C43: =B43*(1+$N43)^'Financial Model & DCF'!I$147-'Financial Model & DCF'!I$158 -> 5533.7524 | D43: =C43*(1+$N43)^'Financial Model & DCF'!J$147-'Financial Model & DCF'!J$158 -> 5772.336 | E43: =D43*(1+$N43)^'Financial Model & DCF'!K$147-'Financial Model & DCF'!K$158 -> 6019.4887 | F43: =E43*(1+$N43)^'Financial Model & DCF'!L$147-'Financial Model & DCF'!L$158 -> 6275.1309 | G43: =F43*(1+$N43)^'Financial Model & DCF'!M$147-'Financial Model & DCF'!M$158 -> 6539.1131 | H43: =G43*(1+$N43)^'Financial Model & DCF'!N$147-'Financial Model & DCF'!N$158 -> 6811.7656 | I43: =H43*(1+$N43)^'Financial Model & DCF'!O$147-'Financial Model & DCF'!O$158 -> 7093.0183 | J43: =I43*(1+$N43)^'Financial Model & DCF'!P$147-'Financial Model & DCF'!P$158 -> 7383.9196 | ... L43: =K43*(1+$N43)^'Financial Model & DCF'!R$147-'Financial Model & DCF'!R$158 -> 7994.6163 | N43: ='Financial Model & DCF'!$R$149+-0.02 -> 0.0666 | O43: ='Financial Model & DCF'!$D$138+0.005 -> 0.0482 | P43: 0.25
A44: Bull | B44: =(B43-('Financial Model & DCF'!$H$52-'Financial Model & DCF'!$H$44))/'Financial Model & DCF'!$D$136 -> 375.08892 | C44: =(C43-('Financial Model & DCF'!$H$52-'Financial Model & DCF'!$H$44))/'Financial Model & DCF'!$D$136 -> 378.11788 | D44: =(D43-('Financial Model & DCF'!$H$52-'Financial Model & DCF'!$H$44))/'Financial Model & DCF'!$D$136 -> 394.36131 | E44: =(E43-('Financial Model & DCF'!$H$52-'Financial Model & DCF'!$H$44))/'Financial Model & DCF'!$D$136 -> 411.18816 | F44: =(F43-('Financial Model & DCF'!$H$52-'Financial Model & DCF'!$H$44))/'Financial Model & DCF'!$D$136 -> 428.59299 | G44: =(G43-('Financial Model & DCF'!$H$52-'Financial Model & DCF'!$H$44))/'Financial Model & DCF'!$D$136 -> 446.56564 | H44: =(H43-('Financial Model & DCF'!$H$52-'Financial Model & DCF'!$H$44))/'Financial Model & DCF'!$D$136 -> 465.12858 | I44: =(I43-('Financial Model & DCF'!$H$52-'Financial Model & DCF'!$H$44))/'Financial Model & DCF'!$D$136 -> 484.27705 | ... L44: =(L43-('Financial Model & DCF'!$H$52-'Financial Model & DCF'!$H$44))/'Financial Model & DCF'!$D$136 -> 545.66036
A45: Current Price | B45: ='Financial Model & DCF'!$D$135 -> 333.74 | C45: ='Financial Model & DCF'!$D$135 -> 333.74 | D45: ='Financial Model & DCF'!$D$135 -> 333.74 | E45: ='Financial Model & DCF'!$D$135 -> 333.74 | F45: ='Financial Model & DCF'!$D$135 -> 333.74 | G45: ='Financial Model & DCF'!$D$135 -> 333.74 | H45: ='Financial Model & DCF'!$D$135 -> 333.74 | I45: ='Financial Model & DCF'!$D$135 -> 333.74 | ... L45: ='Financial Model & DCF'!$D$135 -> 333.74
A46: Probability-Weighted Fair Value (PWFV, today) | B46: =B40*$P$39+B42*$P$41+B44*$P$43 -> 242.89785 | P46: =P39+P41+P43 -> 1
A47: PWFV = scenario values weighted by the blue probabilities (decision-memo convention). These are TODAY values (already discounted at the WACC) - no extra hurdle deduction needed. Verdict grammar: price INSIDE the scenario band = no margin of safety.
A70: Dilution Scenario - Post-Deal Value per Share
A71: The engine excludes deal financing; this block restores it. Set to announced terms (share swap: new shares to the vendor, zero cash raised).
A72: New Shares Issued | B72: 0
A73: Cash Raised (USD billions) | B73: 0
A74: Post-Deal Shares Outstanding | B74: ='Financial Model & DCF'!$D$136+B72 -> 14.688
A75: Post-Deal Equity Value | B75: ='Financial Model & DCF'!$D$170+B73 -> 3145.1441
A76: Post-Deal Intrinsic Value/Share | B76: =B75/B74 -> 214.13018
A77: vs Current Price | B77: =B76/'Financial Model & DCF'!$D$135-1 -> -0.35839221
A80: How to Build a Native Excel Data Table (What-If Analysis)
A82: 1. In an empty corner cell type ='Financial Model & DCF'!D171 (intrinsic value/share).
A83: 2. Across the top row type growth (or multiple) values; down the left column type WACC values.
A84: 3. Select the whole block including the corner cell.
A85: 4. Data tab -> What-If Analysis -> Data Table.
A86: 5. Row input: 'Financial Model & DCF'!$D$138 (growth) or $D$139 (multiple). Column input: 'Financial Model & DCF'!$R$149.
A87: 6. OK - Excel recalculates the live 3-statement engine for every combination.
A88: The grids above use closed-form shortcuts with DIFFERENT terminal-value methods (see each grid title);
A89: a Data Table stresses the live engine with the average-TV headline. Differences between them are expected.
A93: Guards Fired & Responses (audit trail - the workbook outlives the conversation)
A94: Every warning the build-time verify fired, with the analyst's one-line response. UNANSWERED = ship-blocking.
A96: ! NWC PERPETUAL SOURCE: working capital releases cash every single year (>1% of revenue cumulative)
... A113: Take-private lens: buy the whole equity at entry, receive the capital returns the model already forecasts as owner distributions, exit at year 10 on the exit multiple. Unlevered by default - add acquisition debt by editing the entry line. Blue = deal assumptions.
A114: Entry premium to market | B114: 0
A115: Entry equity cost | B115: =-'Financial Model & DCF'!$D$135*(1+B114)*'Financial Model & DCF'!$D$136 -> -4901.9731
A116: Exit EV/EBITDA (blue) | B116: ='Financial Model & DCF'!$D$139 -> 18
A117: Cash flows to owner | B117: =B115 -> -4901.9731 | C117: =-'Financial Model & DCF'!I$77 -> 105 | D117: =-'Financial Model & DCF'!J$77 -> 105 | E117: =-'Financial Model & DCF'!K$77 -> 105 | F117: =-'Financial Model & DCF'!L$77 -> 105 | G117: =-'Financial Model & DCF'!M$77 -> 105 | H117: =-'Financial Model & DCF'!N$77 -> 105 | I117: =-'Financial Model & DCF'!O$77 -> 105 | J117: =-'Financial Model & DCF'!P$77 -> 105 | K117: =-'Financial Model & DCF'!Q$77 -> 105 | L117: =-'Financial Model & DCF'!R$77+$B$116*('Financial Model & DCF'!$R$151+'Financial Model & DCF'!$R$153)-('Financial Model & DCF'!$R$52-'Financial Model & DCF'!$R$44) -> 5175.8925
A118: IRR (annual) | B118: =IFERROR(IRR(B117:L117),"n/m - owner cash flows never turn positive") -> 0.02450278
A119: MOIC | B119: =SUM(C117:L117)/-B115 -> 1.2486589
A120: Exit year net debt uses the engine's forecast balance sheet (debt - cash, year 10); negative net debt (net cash) adds to exit proceeds. Distributions = forecast capital returns (buybacks/dividends redirected to the owner).
A122: IRR sensitivity: entry premium (rows) x exit multiple (cols)
B123: =$B$116+-2 -> 16 | C123: =$B$116+-1 -> 17 | D123: =$B$116+0 -> 18 | E123: =$B$116+1 -> 19 | F123: =$B$116+2 -> 20
A124: -0.2 | B124: =(((SUMPRODUCT(--(C$117:K$117))+(($B$116+-2)*('Financial Model & DCF'!$R$151+'Financial Model & DCF'!$R$153)-('Financial Model & DCF'!$R$52-'Financial Model & DCF'!$R$44)-'Financial Model & DCF'!$R$77)))/('Financial Model & DCF'!$D$135*(1+$A124)*'Financial Model & DCF'!$D$136))^(1/10)-1 -> 0.036610072 | C124: =(((SUMPRODUCT(--(C$117:K$117))+(($B$116+-1)*('Financial Model & DCF'!$R$151+'Financial Model & DCF'!$R$153)-('Financial Model & DCF'!$R$52-'Financial Model & DCF'!$R$44)-'Financial Model & DCF'!$R$77)))/('Financial Model & DCF'!$D$135*(1+$A124)*'Financial Model & DCF'!$D$136))^(1/10)-1 -> 0.041154597 | D124: =(((SUMPRODUCT(--(C$117:K$117))+(($B$116+0)*('Financial Model & DCF'!$R$151+'Financial Model & DCF'!$R$153)-('Financial Model & DCF'!$R$52-'Financial Model & DCF'!$R$44)-'Financial Model & DCF'!$R$77)))/('Financial Model & DCF'!$D$135*(1+$A124)*'Financial Model & DCF'!$D$136))^(1/10)-1 -> 0.045527316 | E124: =(((SUMPRODUCT(--(C$117:K$117))+(($B$116+1)*('Financial Model & DCF'!$R$151+'Financial Model & DCF'!$R$153)-('Financial Model & DCF'!$R$52-'Financial Model & DCF'!$R$44)-'Financial Model & DCF'!$R$77)))/('Financial Model & DCF'!$D$135*(1+$A124)*'Financial Model & DCF'!$D$136))^(1/10)-1 -> 0.049741389 | F124: =(((SUMPRODUCT(--(C$117:K$117))+(($B$116+2)*('Financial Model & DCF'!$R$151+'Financial Model & DCF'!$R$153)-('Financial Model & DCF'!$R$52-'Financial Model & DCF'!$R$44)-'Financial Model & DCF'!$R$77)))/('Financial Model & DCF'!$D$135*(1+$A124)*'Financial Model & DCF'!$D$136))^(1/10)-1 -> 0.053808499
A125: -0.1 | B125: =(((SUMPRODUCT(--(C$117:K$117))+(($B$116+-2)*('Financial Model & DCF'!$R$151+'Financial Model & DCF'!$R$153)-('Financial Model & DCF'!$R$52-'Financial Model & DCF'!$R$44)-'Financial Model & DCF'!$R$77)))/('Financial Model & DCF'!$D$135*(1+$A125)*'Financial Model & DCF'!$D$136))^(1/10)-1 -> 0.024472186 | C125: =(((SUMPRODUCT(--(C$117:K$117))+(($B$116+-1)*('Financial Model & DCF'!$R$151+'Financial Model & DCF'!$R$153)-('Financial Model & DCF'!$R$52-'Financial Model & DCF'!$R$44)-'Financial Model & DCF'!$R$77)))/('Financial Model & DCF'!$D$135*(1+$A125)*'Financial Model & DCF'!$D$136))^(1/10)-1 -> 0.028963499 | D125: =(((SUMPRODUCT(--(C$117:K$117))+(($B$116+0)*('Financial Model & DCF'!$R$151+'Financial Model & DCF'!$R$153)-('Financial Model & DCF'!$R$52-'Financial Model & DCF'!$R$44)-'Financial Model & DCF'!$R$77)))/('Financial Model & DCF'!$D$135*(1+$A125)*'Financial Model & DCF'!$D$136))^(1/10)-1 -> 0.033285016 | E125: =(((SUMPRODUCT(--(C$117:K$117))+(($B$116+1)*('Financial Model & DCF'!$R$151+'Financial Model & DCF'!$R$153)-('Financial Model & DCF'!$R$52-'Financial Model & DCF'!$R$44)-'Financial Model & DCF'!$R$77)))/('Financial Model & DCF'!$D$135*(1+$A125)*'Financial Model & DCF'!$D$136))^(1/10)-1 -> 0.037449746 | F125: =(((SUMPRODUCT(--(C$117:K$117))+(($B$116+2)*('Financial Model & DCF'!$R$151+'Financial Model & DCF'!$R$153)-('Financial Model & DCF'!$R$52-'Financial Model & DCF'!$R$44)-'Financial Model & DCF'!$R$77)))/('Financial Model & DCF'!$D$135*(1+$A125)*'Financial Model & DCF'!$D$136))^(1/10)-1 -> 0.041469233
A126: 0 | B126: =(((SUMPRODUCT(--(C$117:K$117))+(($B$116+-2)*('Financial Model & DCF'!$R$151+'Financial Model & DCF'!$R$153)-('Financial Model & DCF'!$R$52-'Financial Model & DCF'!$R$44)-'Financial Model & DCF'!$R$77)))/('Financial Model & DCF'!$D$135*(1+$A126)*'Financial Model & DCF'!$D$136))^(1/10)-1 -> 0.013734958 | C126: =(((SUMPRODUCT(--(C$117:K$117))+(($B$116+-1)*('Financial Model & DCF'!$R$151+'Financial Model & DCF'!$R$153)-('Financial Model & DCF'!$R$52-'Financial Model & DCF'!$R$44)-'Financial Model & DCF'!$R$77)))/('Financial Model & DCF'!$D$135*(1+$A126)*'Financial Model & DCF'!$D$136))^(1/10)-1 -> 0.018179198 | D126: =(((SUMPRODUCT(--(C$117:K$117))+(($B$116+0)*('Financial Model & DCF'!$R$151+'Financial Model & DCF'!$R$153)-('Financial Model & DCF'!$R$52-'Financial Model & DCF'!$R$44)-'Financial Model & DCF'!$R$77)))/('Financial Model & DCF'!$D$135*(1+$A126)*'Financial Model & DCF'!$D$136))^(1/10)-1 -> 0.022455423 | E126: =(((SUMPRODUCT(--(C$117:K$117))+(($B$116+1)*('Financial Model & DCF'!$R$151+'Financial Model & DCF'!$R$153)-('Financial Model & DCF'!$R$52-'Financial Model & DCF'!$R$44)-'Financial Model & DCF'!$R$77)))/('Financial Model & DCF'!$D$135*(1+$A126)*'Financial Model & DCF'!$D$136))^(1/10)-1 -> 0.026576503 | F126: =(((SUMPRODUCT(--(C$117:K$117))+(($B$116+2)*('Financial Model & DCF'!$R$151+'Financial Model & DCF'!$R$153)-('Financial Model & DCF'!$R$52-'Financial Model & DCF'!$R$44)-'Financial Model & DCF'!$R$77)))/('Financial Model & DCF'!$D$135*(1+$A126)*'Financial Model & DCF'!$D$136))^(1/10)-1 -> 0.030553863
A127: 0.1 | B127: =(((SUMPRODUCT(--(C$117:K$117))+(($B$116+-2)*('Financial Model & DCF'!$R$151+'Financial Model & DCF'!$R$153)-('Financial Model & DCF'!$R$52-'Financial Model & DCF'!$R$44)-'Financial Model & DCF'!$R$77)))/('Financial Model & DCF'!$D$135*(1+$A127)*'Financial Model & DCF'!$D$136))^(1/10)-1 -> 0.0041189295 | C127: =(((SUMPRODUCT(--(C$117:K$117))+(($B$116+-1)*('Financial Model & DCF'!$R$151+'Financial Model & DCF'!$R$153)-('Financial Model & DCF'!$R$52-'Financial Model & DCF'!$R$44)-'Financial Model & DCF'!$R$77)))/('Financial Model & DCF'!$D$135*(1+$A127)*'Financial Model & DCF'!$D$136))^(1/10)-1 -> 0.008521013 | D127: =(((SUMPRODUCT(--(C$117:K$117))+(($B$116+0)*('Financial Model & DCF'!$R$151+'Financial Model & DCF'!$R$153)-('Financial Model & DCF'!$R$52-'Financial Model & DCF'!$R$44)-'Financial Model & DCF'!$R$77)))/('Financial Model & DCF'!$D$135*(1+$A127)*'Financial Model & DCF'!$D$136))^(1/10)-1 -> 0.012756675 | E127: =(((SUMPRODUCT(--(C$117:K$117))+(($B$116+1)*('Financial Model & DCF'!$R$151+'Financial Model & DCF'!$R$153)-('Financial Model & DCF'!$R$52-'Financial Model & DCF'!$R$44)-'Financial Model & DCF'!$R$77)))/('Financial Model & DCF'!$D$135*(1+$A127)*'Financial Model & DCF'!$D$136))^(1/10)-1 -> 0.016838663 | F127: =(((SUMPRODUCT(--(C$117:K$117))+(($B$116+2)*('Financial Model & DCF'!$R$151+'Financial Model & DCF'!$R$153)-('Financial Model & DCF'!$R$52-'Financial Model & DCF'!$R$44)-'Financial Model & DCF'!$R$77)))/('Financial Model & DCF'!$D$135*(1+$A127)*'Financial Model & DCF'!$D$136))^(1/10)-1 -> 0.020778295
A128: 0.2 | B128: =(((SUMPRODUCT(--(C$117:K$117))+(($B$116+-2)*('Financial Model & DCF'!$R$151+'Financial Model & DCF'!$R$153)-('Financial Model & DCF'!$R$52-'Financial Model & DCF'!$R$44)-'Financial Model & DCF'!$R$77)))/('Financial Model & DCF'!$D$135*(1+$A128)*'Financial Model & DCF'!$D$136))^(1/10)-1 -> -0.0045801467 | C128: =(((SUMPRODUCT(--(C$117:K$117))+(($B$116+-1)*('Financial Model & DCF'!$R$151+'Financial Model & DCF'!$R$153)-('Financial Model & DCF'!$R$52-'Financial Model & DCF'!$R$44)-'Financial Model & DCF'!$R$77)))/('Financial Model & DCF'!$D$135*(1+$A128)*'Financial Model & DCF'!$D$136))^(1/10)-1 -> -0.00021620021 | D128: =(((SUMPRODUCT(--(C$117:K$117))+(($B$116+0)*('Financial Model & DCF'!$R$151+'Financial Model & DCF'!$R$153)-('Financial Model & DCF'!$R$52-'Financial Model & DCF'!$R$44)-'Financial Model & DCF'!$R$77)))/('Financial Model & DCF'!$D$135*(1+$A128)*'Financial Model & DCF'!$D$136))^(1/10)-1 -> 0.0039827663 | E128: =(((SUMPRODUCT(--(C$117:K$117))+(($B$116+1)*('Financial Model & DCF'!$R$151+'Financial Model & DCF'!$R$153)-('Financial Model & DCF'!$R$52-'Financial Model & DCF'!$R$44)-'Financial Model & DCF'!$R$77)))/('Financial Model & DCF'!$D$135*(1+$A128)*'Financial Model & DCF'!$D$136))^(1/10)-1 -> 0.0080293912 | F128: =(((SUMPRODUCT(--(C$117:K$117))+(($B$116+2)*('Financial Model & DCF'!$R$151+'Financial Model & DCF'!$R$153)-('Financial Model & DCF'!$R$52-'Financial Model & DCF'!$R$44)-'Financial Model & DCF'!$R$77)))/('Financial Model & DCF'!$D$135*(1+$A128)*'Financial Model & DCF'!$D$136))^(1/10)-1 -> 0.011934892
A130: Grid IRR is money-multiple annualized ((total inflows / entry)^(1/N)-1) - a distribution-timing-blind approximation; the headline IRR above is the exact cash-flow IRR.
